[
  {"guid": "D01_001", "base_target": "rapidement", "base_source": "ವೇಗವಾಗಿ", "corpus": "WORDS4", "group": "Style", "level": 11, "word_type": "adverb", "tags": ["style", "level_11"]},
  {"guid": "D01_002", "base_target": "lentement", "base_source": "ನೀಸವಾಗಿ", "corpus": "WORDS4", "group": "Style", "level": 11, "word_type": "adverb", "tags": ["style", "level_11"]},
  {"guid": "D01_003", "base_target": "bien", "base_source": "ಸುಂದರವಾಗಿ", "corpus": "WORDS4", "group": "Style", "level": 11, "word_type": "adverb", "tags": ["style", "level_11"]},
  {"guid": "D01_004", "base_target": "mal", "base_source": "ಬೆರಗಾಗಿ", "corpus": "WORDS4", "group": "Style", "level": 11, "word_type": "adverb", "tags": ["style", "level_11"]},
  {"guid": "D01_005", "base_target": "fort", "base_source": "ಬರಡಾಗಿ", "corpus": "WORDS4", "group": "Style", "level": 11, "word_type": "adverb", "tags": ["style", "level_11"]},
  {"guid": "D01_006", "base_target": "silencieusement", "base_source": "ಶಾಂತವಾಗಿ", "corpus": "WORDS4", "group": "Style", "level": 11, "word_type": "adverb", "tags": ["style", "level_11"]},
  {"guid": "D01_007", "base_target": "facilement", "base_source": "ಸಲಸಿದಾಗ", "corpus": "WORDS4", "group": "Style", "level": 11, "word_type": "adverb", "tags": ["style", "level_11"]},
  {"guid": "D01_008", "base_target": "dur", "base_source": "ಕಷ್ಟವಾಗಿ", "corpus": "WORDS4", "group": "Style", "level": 11, "word_type": "adverb", "tags": ["style", "level_11"]},
  {"guid": "D01_009", "base_target": "ensemble", "base_source": "ಒಟ್ಟಾಗಿ", "corpus": "WORDS4", "group": "Style", "level": 11, "word_type": "adverb", "tags": ["style", "level_11"]},
  {"guid": "D01_010", "base_target": "seul", "base_source": "ಒಬ್ಬನೆ", "corpus": "WORDS4", "group": "Style", "level": 11, "word_type": "adverb", "tags": ["style", "level_11"]},
  {"guid": "N06_008", "base_target": "poisson", "base_source": "ಮೀನು", "corpus": "WORDS3", "group": "Food", "level": 11, "word_type": "noun", "tags": ["food", "level_11"]},
  {"guid": "N06_009", "base_target": "œuf", "base_source": "ಮೊಟ್ಟೆ", "corpus": "WORDS3", "group": "Food", "level": 11, "word_type": "noun", "tags": ["food", "level_11"]},
  {"guid": "N06_010", "base_target": "fromage", "base_source": "ಚೀಸ್", "corpus": "WORDS3", "group": "Food", "level": 11, "word_type": "noun", "tags": ["food", "level_11"]},
  {"guid": "N06_011", "base_target": "beurre", "base_source": "ಬೆಣ್ಣೆ", "corpus": "WORDS3", "group": "Food", "level": 11, "word_type": "noun", "tags": ["food", "level_11"]},
  {"guid": "N06_017", "base_target": "orange", "base_source": "ಕಿತ್ತಳೆ", "corpus": "WORDS3", "group": "Food", "level": 11, "word_type": "noun", "tags": ["food", "level_11"]},
  {"guid": "N06_019", "base_target": "oignon", "base_source": "ಈರುಳ್ಳಿ", "corpus": "WORDS3", "group": "Food", "level": 11, "word_type": "noun", "tags": ["food", "level_11"]},
  {"guid": "N06_022", "base_target": "gâteau", "base_source": "ಕೇಕ್", "corpus": "WORDS3", "group": "Food", "level": 11, "word_type": "noun", "tags": ["food", "level_11"]},
  {"guid": "N06_023", "base_target": "chocolat", "base_source": "ಚಾಕೊಲೇಟ್", "corpus": "WORDS3", "group": "Food", "level": 11, "word_type": "noun", "tags": ["food", "level_11"]},
  {"guid": "N06_024", "base_target": "pâtes", "base_source": "ಪಾಸ್ತಾ", "corpus": "WORDS3", "group": "Food", "level": 11, "word_type": "noun", "tags": ["food", "level_11"]},
  {"guid": "N06_026", "base_target": "pizza", "base_source": "ಪಿಜ್ಜಾ", "corpus": "WORDS3", "group": "Food", "level": 11, "word_type": "noun", "tags": ["food", "level_11"]},
  {"guid": "N06_027", "base_target": "sandwich", "base_source": "ಸ್ಯಾಂಡ್‌ವಿಚ್", "corpus": "WORDS3", "group": "Food", "level": 11, "word_type": "noun", "tags": ["food", "level_11"]},
  {"guid": "N06_028", "base_target": "salade", "base_source": "ಸಲಾಡ್", "corpus": "WORDS3", "group": "Food", "level": 11, "word_type": "noun", "tags": ["food", "level_11"]},
  {"guid": "N06_029", "base_target": "yaourt", "base_source": "ಮೊಸರು", "corpus": "WORDS3", "group": "Food", "level": 11, "word_type": "noun", "tags": ["food", "level_11"]},
  {"guid": "N06_030", "base_target": "miel", "base_source": "ಜೇನುತುಪ್ಪ", "corpus": "WORDS3", "group": "Food", "level": 11, "word_type": "noun", "tags": ["food", "level_11"]},
  {"guid": "N06_031", "base_target": "confiture", "base_source": "ಜಾಮ್", "corpus": "WORDS3", "group": "Food", "level": 11, "word_type": "noun", "tags": ["food", "level_11"]},
  {"guid": "N06_034", "base_target": "ketchup", "base_source": "ಕೆಚಪ್", "corpus": "WORDS3", "group": "Food", "level": 11, "word_type": "noun", "tags": ["food", "level_11"]},
  {"guid": "N06_035", "base_target": "mayonnaise", "base_source": "ಮಯೋನೈಸ್", "corpus": "WORDS3", "group": "Food", "level": 11, "word_type": "noun", "tags": ["food", "level_11"]},
  {"guid": "N06_036", "base_target": "vinaigre", "base_source": "ವಿನೆಗರ್", "corpus": "WORDS3", "group": "Food", "level": 11, "word_type": "noun", "tags": ["food", "level_11"]},
  {"guid": "N06_037", "base_target": "huile de cuisson", "base_source": "ಅಡುಗೆ ಎಣ್ಣೆ", "corpus": "WORDS3", "group": "Food", "level": 11, "word_type": "noun", "tags": ["food", "level_11"]},
  {"guid": "N06_038", "base_target": "farine", "base_source": "ಹಿಟ್ಟು", "corpus": "WORDS3", "group": "Food", "level": 11, "word_type": "noun", "tags": ["food", "level_11"]},
  {"guid": "N06_039", "base_target": "maïs", "base_source": "ಮೆಕ್ಕೆ ಜೋಳ", "corpus": "WORDS3", "group": "Food", "level": 11, "word_type": "noun", "tags": ["food", "level_11"]},
  {"guid": "N06_040", "base_target": "haricot", "base_source": "ಅವರೆಕಾಯಿ", "corpus": "WORDS3", "group": "Food", "level": 11, "word_type": "noun", "tags": ["food", "level_11"]},
  {"guid": "N06_041", "base_target": "petit pois", "base_source": "ಬಟಾಣಿ", "corpus": "WORDS3", "group": "Food", "level": 11, "word_type": "noun", "tags": ["food", "level_11"]},
  {"guid": "N06_042", "base_target": "citron", "base_source": "ನಿಂಬೆ", "corpus": "WORDS3", "group": "Food", "level": 11, "word_type": "noun", "tags": ["food", "level_11"]},
  {"guid": "N06_043", "base_target": "citron vert", "base_source": "ಲಿಂಬೆ", "corpus": "WORDS3", "group": "Food", "level": 11, "word_type": "noun", "tags": ["food", "level_11"]},
  {"guid": "N06_044", "base_target": "raisin", "base_source": "ದ್ರಾಕ್ಷಿ", "corpus": "WORDS3", "group": "Food", "level": 11, "word_type": "noun", "tags": ["food", "level_11"]},
  {"guid": "N06_045", "base_target": "fraise", "base_source": "ಸ್ಟ್ರಾಬೆರಿ", "corpus": "WORDS3", "group": "Food", "level": 11, "word_type": "noun", "tags": ["food", "level_11"]},
  {"guid": "N06_048", "base_target": "cerise", "base_source": "ಚೆರ್ರಿ", "corpus": "WORDS3", "group": "Food", "level": 11, "word_type": "noun", "tags": ["food", "level_11"]},
  {"guid": "N06_049", "base_target": "pêche", "base_source": "ಪೀಚ್", "corpus": "WORDS3", "group": "Food", "level": 11, "word_type": "noun", "tags": ["food", "level_11"]},
  {"guid": "N06_050", "base_target": "poire", "base_source": "ಪೇರಲ", "corpus": "WORDS3", "group": "Food", "level": 11, "word_type": "noun", "tags": ["food", "level_11"]},
  {"guid": "N06_051", "base_target": "pastèque", "base_source": "ಕಲ್ಲಂಗಡಿ", "corpus": "WORDS3", "group": "Food", "level": 11, "word_type": "noun", "tags": ["food", "level_11"]},
  {"guid": "N06_052", "base_target": "melon", "base_source": "ಕರಬೂಜ", "corpus": "WORDS3", "group": "Food", "level": 11, "word_type": "noun", "tags": ["food", "level_11"]},
  {"guid": "N06_053", "base_target": "ananas", "base_source": "ಅನಾನಸ್", "corpus": "WORDS3", "group": "Food", "level": 11, "word_type": "noun", "tags": ["food", "level_11"]},
  {"guid": "N06_054", "base_target": "mangue", "base_source": "ಮಾವಿನಹಣ್ಣು", "corpus": "WORDS3", "group": "Food", "level": 11, "word_type": "noun", "tags": ["food", "level_11"]},
  {"guid": "N06_055", "base_target": "noix de coco", "base_source": "ತೆಂಗಿನಕಾಯಿ", "corpus": "WORDS3", "group": "Food", "level": 11, "word_type": "noun", "tags": ["food", "level_11"]},
  {"guid": "N06_056", "base_target": "noix", "base_source": "ಅಕ್ರೋಡ್", "corpus": "WORDS3", "group": "Food", "level": 11, "word_type": "noun", "tags": ["food", "level_11"]},
  {"guid": "N06_057", "base_target": "amande", "base_source": "ಬಾದಾಮಿ", "corpus": "WORDS3", "group": "Food", "level": 11, "word_type": "noun", "tags": ["food", "level_11"]},
  {"guid": "N06_058", "base_target": "cacahuète", "base_source": "ಕಡಲೆಕಾಯಿ", "corpus": "WORDS3", "group": "Food", "level": 11, "word_type": "noun", "tags": ["food", "level_11"]},
  {"guid": "N06_059", "base_target": "champignon", "base_source": "ಅಣಬೆ", "corpus": "WORDS3", "group": "Food", "level": 11, "word_type": "noun", "tags": ["food", "level_11"]},
  {"guid": "N06_060", "base_target": "ail", "base_source": "ಬೆಳ್ಳುಳ್ಳಿ", "corpus": "WORDS3", "group": "Food", "level": 11, "word_type": "noun", "tags": ["food", "level_11"]},
  {"guid": "N06_061", "base_target": "chou", "base_source": "ಎಲೆಕೋಸು", "corpus": "WORDS3", "group": "Food", "level": 11, "word_type": "noun", "tags": ["food", "level_11"]},
  {"guid": "N06_062", "base_target": "laitue", "base_source": "ಲೆಟ್ಯೂಸ್", "corpus": "WORDS3", "group": "Food", "level": 11, "word_type": "noun", "tags": ["food", "level_11"]},
  {"guid": "N06_063", "base_target": "épinard", "base_source": "ಪಾಲಕ್", "corpus": "WORDS3", "group": "Food", "level": 11, "word_type": "noun", "tags": ["food", "level_11"]},
  {"guid": "N06_064", "base_target": "brocoli", "base_source": "ಬ್ರೊಕೊಲಿ", "corpus": "WORDS3", "group": "Food", "level": 11, "word_type": "noun", "tags": ["food", "level_11"]},
  {"guid": "N06_066", "base_target": "poivre", "base_source": "ಮೆಣಸು", "corpus": "WORDS3", "group": "Food", "level": 11, "word_type": "noun", "tags": ["food", "level_11"]},
  {"guid": "N06_067", "base_target": "concombre", "base_source": "ಸೌತೆಕಾಯಿ", "corpus": "WORDS3", "group": "Food", "level": 11, "word_type": "noun", "tags": ["food", "level_11"]},
  {"guid": "N06_072", "base_target": "saucisse", "base_source": "ಸಾಸೇಜ್", "corpus": "WORDS3", "group": "Food", "level": 11, "word_type": "noun", "tags": ["food", "level_11"]},
  {"guid": "N06_073", "base_target": "jambon", "base_source": "ಹ್ಯಾಮ್", "corpus": "WORDS3", "group": "Food", "level": 11, "word_type": "noun", "tags": ["food", "level_11"]},
  {"guid": "N06_074", "base_target": "bacon", "base_source": "ಬೇಕನ್", "corpus": "WORDS3", "group": "Food", "level": 11, "word_type": "noun", "tags": ["food", "level_11"]},
  {"guid": "N06_075", "base_target": "viande de poulet", "base_source": "ಕೋಳಿ ಮಾಂಸ", "corpus": "WORDS3", "group": "Food", "level": 11, "word_type": "noun", "tags": ["food", "level_11"]},
  {"guid": "N06_076", "base_target": "bœuf", "base_source": "ಗೋಮಾಂಸ", "corpus": "WORDS3", "group": "Food", "level": 11, "word_type": "noun", "tags": ["food", "level_11"]},
  {"guid": "N06_077", "base_target": "porc", "base_source": "ಹಂದಿ ಮಾಂಸ", "corpus": "WORDS3", "group": "Food", "level": 11, "word_type": "noun", "tags": ["food", "level_11"]},
  {"guid": "N06_078", "base_target": "agneau", "base_source": "ಕುರಿ ಮಾಂಸ", "corpus": "WORDS3", "group": "Food", "level": 11, "word_type": "noun", "tags": ["food", "level_11"]},
  {"guid": "N06_079", "base_target": "saumon", "base_source": "ಸಾಲ್ಮನ್", "corpus": "WORDS3", "group": "Food", "level": 11, "word_type": "noun", "tags": ["food", "level_11"]},
  {"guid": "N06_080", "base_target": "thon", "base_source": "ಟ್ಯೂನ", "corpus": "WORDS3", "group": "Food", "level": 11, "word_type": "noun", "tags": ["food", "level_11"]},
  {"guid": "N06_081", "base_target": "crevette", "base_source": "ಸೀಗಡಿ", "corpus": "WORDS3", "group": "Food", "level": 11, "word_type": "noun", "tags": ["food", "level_11"]},
  {"guid": "N06_082", "base_target": "crabe", "base_source": "ಏಡಿ", "corpus": "WORDS3", "group": "Food", "level": 11, "word_type": "noun", "tags": ["food", "level_11"]},
  {"guid": "N06_083", "base_target": "homard", "base_source": "ಲಾಬ್ಸ್ಟರ್", "corpus": "WORDS3", "group": "Food", "level": 11, "word_type": "noun", "tags": ["food", "level_11"]},
  {"guid": "N06_084", "base_target": "carotte", "base_source": "ಗಜ್ಜರಿ", "corpus": "WORDS3", "group": "Food", "level": 11, "word_type": "noun", "tags": ["food", "level_11"]},
  {"guid": "N06_093", "base_target": "poivron", "base_source": "ದೊಡ್ಡ ಮೆಣಸಿನಕಾಯಿ", "corpus": "WORDS3", "group": "Food", "level": 11, "word_type": "noun", "tags": ["food", "level_11"]},
  {"guid": "N23_001", "base_target": "bonheur", "base_source": "ಸಂತೋಷ", "corpus": "WORDS4", "group": "Emotion/Feeling", "level": 12, "word_type": "noun", "tags": ["emotion_feeling", "level_12"]},
  {"guid": "N23_002", "base_target": "tristesse", "base_source": "ಶೋಕ", "corpus": "WORDS4", "group": "Emotion/Feeling", "level": 12, "word_type": "noun", "tags": ["emotion_feeling", "level_12"]},
  {"guid": "N23_003", "base_target": "colère", "base_source": "ಕ್ರೋಧ", "corpus": "WORDS4", "group": "Emotion/Feeling", "level": 12, "word_type": "noun", "tags": ["emotion_feeling", "level_12"]},
  {"guid": "N23_004", "base_target": "enthousiasme", "base_source": "ಉತ್ಸಾಹ", "corpus": "WORDS4", "group": "Emotion/Feeling", "level": 12, "word_type": "noun", "tags": ["emotion_feeling", "level_12"]},
  {"guid": "N23_005", "base_target": "fatigue", "base_source": "ಆಲಸ್ಯ/ಹಗಲುನಿದ್ರೆಯ ಕೊರತೆ/ಕ್ಲಾಂತಿ", "corpus": "WORDS4", "group": "Emotion/Feeling", "level": 12, "word_type": "noun", "tags": ["emotion_feeling", "level_12"]},
  {"guid": "N23_006", "base_target": "peur", "base_source": "ಭಯ", "corpus": "WORDS4", "group": "Emotion/Feeling", "level": 12, "word_type": "noun", "tags": ["emotion_feeling", "level_12"]},
  {"guid": "N23_007", "base_target": "surprise", "base_source": "ಆಶ್ಚರ್ಯ", "corpus": "WORDS4", "group": "Emotion/Feeling", "level": 12, "word_type": "noun", "tags": ["emotion_feeling", "level_12"]},
  {"guid": "N23_008", "base_target": "inquiétude", "base_source": "ಚಿಂತೆಯ", "corpus": "WORDS4", "group": "Emotion/Feeling", "level": 12, "word_type": "noun", "tags": ["emotion_feeling", "level_12"]},
  {"guid": "N23_009", "base_target": "calme", "base_source": "ಶಾಂತಿ", "corpus": "WORDS4", "group": "Emotion/Feeling", "level": 12, "word_type": "noun", "tags": ["emotion_feeling", "level_12"]},
  {"guid": "N23_010", "base_target": "nervosité", "base_source": "ಅವಿಶ್ರಾಂತತೆ", "corpus": "WORDS4", "group": "Emotion/Feeling", "level": 12, "word_type": "noun", "tags": ["emotion_feeling", "level_12"]},
  {"guid": "N23_011", "base_target": "confusion", "base_source": "ಗೊಂದಲ", "corpus": "WORDS4", "group": "Emotion/Feeling", "level": 12, "word_type": "noun", "tags": ["emotion_feeling", "level_12"]},
  {"guid": "N23_012", "base_target": "embarras", "base_source": "ಅಸಹಜತೆ", "corpus": "WORDS4", "group": "Emotion/Feeling", "level": 12, "word_type": "noun", "tags": ["emotion_feeling", "level_12"]},
  {"guid": "N23_013", "base_target": "fierté", "base_source": "ಗರ್ವ", "corpus": "WORDS4", "group": "Emotion/Feeling", "level": 12, "word_type": "noun", "tags": ["emotion_feeling", "level_12"]},
  {"guid": "N23_014", "base_target": "jalousie", "base_source": "ಅಸೆಹ", "corpus": "WORDS4", "group": "Emotion/Feeling", "level": 12, "word_type": "noun", "tags": ["emotion_feeling", "level_12"]},
  {"guid": "N23_015", "base_target": "solitude", "base_source": "ಏಕಾಂತ", "corpus": "WORDS4", "group": "Emotion/Feeling", "level": 12, "word_type": "noun", "tags": ["emotion_feeling", "level_12"]},
  {"guid": "N23_016", "base_target": "gratitude", "base_source": "ಕೃತಜ್ಞಾನ", "corpus": "WORDS4", "group": "Emotion/Feeling", "level": 12, "word_type": "noun", "tags": ["emotion_feeling", "level_12"]},
  {"guid": "N23_017", "base_target": "frustration", "base_source": "ನಿರಾಶೆ", "corpus": "WORDS4", "group": "Emotion/Feeling", "level": 12, "word_type": "noun", "tags": ["emotion_feeling", "level_12"]},
  {"guid": "N23_018", "base_target": "espoir", "base_source": "ಆಶೆ", "corpus": "WORDS4", "group": "Emotion/Feeling", "level": 12, "word_type": "noun", "tags": ["emotion_feeling", "level_12"]},
  {"guid": "N23_019", "base_target": "déception", "base_source": "ನಿರಾಸೆ", "corpus": "WORDS4", "group": "Emotion/Feeling", "level": 12, "word_type": "noun", "tags": ["emotion_feeling", "level_12"]},
  {"guid": "N23_020", "base_target": "curiosité", "base_source": "ಹುಚ್ಚುಹಣೆ/ಆಕಾಂಕ್ಷೆ/ಅತ್ಯಾಸಕ್ತಿ", "corpus": "WORDS4", "group": "Emotion/Feeling", "level": 12, "word_type": "noun", "tags": ["emotion_feeling", "level_12"]},
  {"guid": "N23_021", "base_target": "ennui", "base_source": "ಬೆರೆನಿಕೆ", "corpus": "WORDS4", "group": "Emotion/Feeling", "level": 12, "word_type": "noun", "tags": ["emotion_feeling", "level_12"]},
  {"guid": "N23_022", "base_target": "gaieté", "base_source": "ಹರ್ಷ", "corpus": "WORDS4", "group": "Emotion/Feeling", "level": 12, "word_type": "noun", "tags": ["emotion_feeling", "level_12"]},
  {"guid": "N23_024", "base_target": "anxiété", "base_source": "ಚಿಂತೆ", "corpus": "WORDS4", "group": "Emotion/Feeling", "level": 12, "word_type": "noun", "tags": ["emotion_feeling", "level_12"]},
  {"guid": "N23_025", "base_target": "joie", "base_source": "ಆನಂದ", "corpus": "WORDS4", "group": "Emotion/Feeling", "level": 12, "word_type": "noun", "tags": ["emotion_feeling", "level_12"]},
  {"guid": "N23_026", "base_target": "douleur", "base_source": "ನೋವು", "corpus": "WORDS4", "group": "Emotion/Feeling", "level": 12, "word_type": "noun", "tags": ["emotion_feeling", "level_12"]},
  {"guid": "N23_027", "base_target": "terreur", "base_source": "ಭಯಾಂಕತೆ", "corpus": "WORDS4", "group": "Emotion/Feeling", "level": 12, "word_type": "noun", "tags": ["emotion_feeling", "level_12"]},
  {"guid": "N23_028", "base_target": "désir", "base_source": "ಆಕಾಂಕ್ಷೆ", "corpus": "WORDS4", "group": "Emotion/Feeling", "level": 12, "word_type": "noun", "tags": ["emotion_feeling", "level_12"]},
  {"guid": "N23_029", "base_target": "courage", "base_source": "ಧೈರ್ಯ", "corpus": "WORDS4", "group": "Emotion/Feeling", "level": 12, "word_type": "noun", "tags": ["emotion_feeling", "level_12"]},
  {"guid": "N23_030", "base_target": "choc", "base_source": "ಆಘಾತ", "corpus": "WORDS4", "group": "Emotion/Feeling", "level": 12, "word_type": "noun", "tags": ["emotion_feeling", "level_12"]},
  {"guid": "N43_001", "base_target": "mixeur", "base_source": "ಬ್ಲೆಂಡರ್", "corpus": "WORDS4", "group": "Appliance", "level": 12, "word_type": "noun", "tags": ["appliance", "level_12"]},
  {"guid": "N43_002", "base_target": "four", "base_source": "ಒವೆನ್", "corpus": "WORDS4", "group": "Appliance", "level": 12, "word_type": "noun", "tags": ["appliance", "level_12"]},
  {"guid": "N43_003", "base_target": "réfrigérateur", "base_source": "ರೆಫ್ರಿಜರೇಟರ್", "corpus": "WORDS4", "group": "Appliance", "level": 12, "word_type": "noun", "tags": ["appliance", "level_12"]},
  {"guid": "N43_004", "base_target": "four à micro-ondes", "base_source": "ಮೈಕ್ರೋವೇವ್", "corpus": "WORDS4", "group": "Appliance", "level": 12, "word_type": "noun", "tags": ["appliance", "level_12"]},
  {"guid": "N43_005", "base_target": "machine à laver", "base_source": "ವಾಷಿಂಗ್ ಮೆಷಿನ್", "corpus": "WORDS4", "group": "Appliance", "level": 12, "word_type": "noun", "tags": ["appliance", "level_12"]},
  {"guid": "N43_006", "base_target": "sèche-linge", "base_source": "ಡ್ರೈಯರ್", "corpus": "WORDS4", "group": "Appliance", "level": 12, "word_type": "noun", "tags": ["appliance", "level_12"]},
  {"guid": "N43_007", "base_target": "lave-vaisselle", "base_source": "ಡಿಶ್‌ವಾಷರ್", "corpus": "WORDS4", "group": "Appliance", "level": 12, "word_type": "noun", "tags": ["appliance", "level_12"]},
  {"guid": "N43_008", "base_target": "grille-pain", "base_source": "ಟೋಸ್ಟರ್", "corpus": "WORDS4", "group": "Appliance", "level": 12, "word_type": "noun", "tags": ["appliance", "level_12"]},
  {"guid": "N43_009", "base_target": "cafetière", "base_source": "ಕಾಫಿ ಮೇಕರ್", "corpus": "WORDS4", "group": "Appliance", "level": 12, "word_type": "noun", "tags": ["appliance", "level_12"]},
  {"guid": "N43_010", "base_target": "aspirateur", "base_source": "ವ್ಯಾಕ್ಯೂಮ್ ಕ್ಲೀನರ್", "corpus": "WORDS4", "group": "Appliance", "level": 12, "word_type": "noun", "tags": ["appliance", "level_12"]},
  {"guid": "N43_011", "base_target": "climatiseur", "base_source": "ಏರ್ ಕಂಡಿಷನರ್", "corpus": "WORDS4", "group": "Appliance", "level": 12, "word_type": "noun", "tags": ["appliance", "level_12"]},
  {
    "guid": "V01_012",
    "base_target": "utiliser",
    "base_source": "ಬಳಸಲು",
    "corpus": "VERBS",
    "group": "Physical Action",
    "level": 12,
    "word_type": "verb",
    "conjugation_mode": {"format": "raw_forms_v2", "tables": {"fut": {"1p": {"source": "ಬಳಸಲು (1p future)", "target": "utiliserons"}, "1s": {"source": "ಬಳಸಲು (1s future)", "target": "utiliserai"}, "2p": {"source": "ಬಳಸಲು (2p future)", "target": "utiliserez"}, "2s": {"source": "ಬಳಸಲು (2s future)", "target": "utiliseras"}, "3p": {"source": "ಬಳಸಲು (3p future)", "target": "utiliseront"}, "3s": {"source": "ಬಳಸಲು (3s future)", "target": "utilisera"}}, "pres": {"1p": {"source": "ಬಳಸಲು (1p present)", "target": "utilisons"}, "2p": {"source": "ಬಳಸಲು (2p present)", "target": "utilisez"}, "2s": {"source": "ಬಳಸಲು (2s present)", "target": "utilises"}, "3p": {"source": "ಬಳಸಲು (3p present)", "target": "utilisent"}, "3s": {"source": "ಬಳಸಲು (3s present)", "target": "utilise"}}}},
    "tags": ["physical_action", "level_12"],
    "grammatical_forms": {
      "1p_future": {"level": 12, "target": "utiliserons", "english": "ಬಳಸಲು (1p future)"},
      "1p_present": {"level": 12, "target": "utilisons", "english": "ಬಳಸಲು (1p present)"},
      "1s_future": {"level": 12, "target": "utiliserai", "english": "ಬಳಸಲು (1s future)"},
      "2p_future": {"level": 12, "target": "utiliserez", "english": "ಬಳಸಲು (2p future)"},
      "2p_present": {"level": 12, "target": "utilisez", "english": "ಬಳಸಲು (2p present)"},
      "2s_future": {"level": 12, "target": "utiliseras", "english": "ಬಳಸಲು (2s future)"},
      "2s_present": {"level": 12, "target": "utilises", "english": "ಬಳಸಲು (2s present)"},
      "3p_future": {"level": 12, "target": "utiliseront", "english": "ಬಳಸಲು (3p future)"},
      "3p_present": {"level": 12, "target": "utilisent", "english": "ಬಳಸಲು (3p present)"},
      "3s_future": {"level": 12, "target": "utilisera", "english": "ಬಳಸಲು (3s future)"},
      "3s_present": {"level": 12, "target": "utilise", "english": "ಬಳಸಲು (3s present)"}
    }
  },
  {
    "guid": "V04_002",
    "base_target": "enseigner",
    "base_source": "ಮಾಡಲು ಕಲಿಸಲು",
    "corpus": "VERBS",
    "group": "Mental State",
    "level": 12,
    "word_type": "verb",
    "conjugation_mode": {"format": "raw_forms_v2", "tables": {"fut": {"1p": {"source": "ಮಾಡಲು ಕಲಿಸಲು (1p future)", "target": "enseignerons"}, "1s": {"source": "ಮಾಡಲು ಕಲಿಸಲು (1s future)", "target": "enseignerai"}, "2p": {"source": "ಮಾಡಲು ಕಲಿಸಲು (2p future)", "target": "enseignerez"}, "2s": {"source": "ಮಾಡಲು ಕಲಿಸಲು (2s future)", "target": "enseigneras"}, "3p": {"source": "ಮಾಡಲು ಕಲಿಸಲು (3p future)", "target": "enseigneront"}, "3s": {"source": "ಮಾಡಲು ಕಲಿಸಲು (3s future)", "target": "enseignera"}}, "pres": {"1p": {"source": "ಮಾಡಲು ಕಲಿಸಲು (1p present)", "target": "enseignons"}, "2p": {"source": "ಮಾಡಲು ಕಲಿಸಲು (2p present)", "target": "enseignez"}, "2s": {"source": "ಮಾಡಲು ಕಲಿಸಲು (2s present)", "target": "enseignes"}, "3p": {"source": "ಮಾಡಲು ಕಲಿಸಲು (3p present)", "target": "enseignent"}, "3s": {"source": "ಮಾಡಲು ಕಲಿಸಲು (3s present)", "target": "enseigne"}}}},
    "tags": ["mental_state", "level_12"],
    "grammatical_forms": {
      "1p_future": {"level": 12, "target": "enseignerons", "english": "ಮಾಡಲು ಕಲಿಸಲು (1p future)"},
      "1p_present": {"level": 12, "target": "enseignons", "english": "ಮಾಡಲು ಕಲಿಸಲು (1p present)"},
      "1s_future": {"level": 12, "target": "enseignerai", "english": "ಮಾಡಲು ಕಲಿಸಲು (1s future)"},
      "2p_future": {"level": 12, "target": "enseignerez", "english": "ಮಾಡಲು ಕಲಿಸಲು (2p future)"},
      "2p_present": {"level": 12, "target": "enseignez", "english": "ಮಾಡಲು ಕಲಿಸಲು (2p present)"},
      "2s_future": {"level": 12, "target": "enseigneras", "english": "ಮಾಡಲು ಕಲಿಸಲು (2s future)"},
      "2s_present": {"level": 12, "target": "enseignes", "english": "ಮಾಡಲು ಕಲಿಸಲು (2s present)"},
      "3p_future": {"level": 12, "target": "enseigneront", "english": "ಮಾಡಲು ಕಲಿಸಲು (3p future)"},
      "3p_present": {"level": 12, "target": "enseignent", "english": "ಮಾಡಲು ಕಲಿಸಲು (3p present)"},
      "3s_future": {"level": 12, "target": "enseignera", "english": "ಮಾಡಲು ಕಲಿಸಲು (3s future)"},
      "3s_present": {"level": 12, "target": "enseigne", "english": "ಮಾಡಲು ಕಲಿಸಲು (3s present)"}
    }
  },
  {
    "guid": "V04_012",
    "base_target": "se souvenir",
    "base_source": "ಸ್ಮರಿಸು",
    "corpus": "VERBS",
    "group": "Mental State",
    "level": 12,
    "word_type": "verb",
    "conjugation_mode": {"format": "raw_forms_v2", "tables": {"fut": {"1p": {"source": "ಸ್ಮರಿಸು (1p future)", "target": "se souvenirons"}, "1s": {"source": "ಸ್ಮರಿಸು (1s future)", "target": "se souvenirai"}, "2p": {"source": "ಸ್ಮರಿಸು (2p future)", "target": "se souvenirez"}, "2s": {"source": "ಸ್ಮರಿಸು (2s future)", "target": "se souveniras"}, "3p": {"source": "ಸ್ಮರಿಸು (3p future)", "target": "se souveniront"}, "3s": {"source": "ಸ್ಮರಿಸು (3s future)", "target": "se souvenira"}}, "pres": {"1p": {"source": "ಸ್ಮರಿಸು (1p present)", "target": "se souvenissons"}, "2p": {"source": "ಸ್ಮರಿಸು (2p present)", "target": "se souvenissez"}, "2s": {"source": "ಸ್ಮರಿಸು (2s present)", "target": "se souvenis"}, "3p": {"source": "ಸ್ಮರಿಸು (3p present)", "target": "se souvenissent"}, "3s": {"source": "ಸ್ಮರಿಸು (3s present)", "target": "se souvenit"}}}},
    "tags": ["mental_state", "level_12"],
    "grammatical_forms": {
      "1p_future": {"level": 12, "target": "se souvenirons", "english": "ಸ್ಮರಿಸು (1p future)"},
      "1p_present": {"level": 12, "target": "se souvenissons", "english": "ಸ್ಮರಿಸು (1p present)"},
      "1s_future": {"level": 12, "target": "se souvenirai", "english": "ಸ್ಮರಿಸು (1s future)"},
      "2p_future": {"level": 12, "target": "se souvenirez", "english": "ಸ್ಮರಿಸು (2p future)"},
      "2p_present": {"level": 12, "target": "se souvenissez", "english": "ಸ್ಮರಿಸು (2p present)"},
      "2s_future": {"level": 12, "target": "se souveniras", "english": "ಸ್ಮರಿಸು (2s future)"},
      "2s_present": {"level": 12, "target": "se souvenis", "english": "ಸ್ಮರಿಸು (2s present)"},
      "3p_future": {"level": 12, "target": "se souveniront", "english": "ಸ್ಮರಿಸು (3p future)"},
      "3p_present": {"level": 12, "target": "se souvenissent", "english": "ಸ್ಮರಿಸು (3p present)"},
      "3s_future": {"level": 12, "target": "se souvenira", "english": "ಸ್ಮರಿಸು (3s future)"},
      "3s_present": {"level": 12, "target": "se souvenit", "english": "ಸ್ಮರಿಸು (3s present)"}
    }
  },
  {
    "guid": "V04_015",
    "base_target": "croire",
    "base_source": "ನಂಬಲು",
    "corpus": "VERBS",
    "group": "Mental State",
    "level": 12,
    "word_type": "verb",
    "conjugation_mode": {"format": "raw_forms_v2", "tables": {"fut": {"1p": {"source": "ನಂಬಲು (1p future)", "target": "croirons"}, "1s": {"source": "ನಂಬಲು (1s future)", "target": "croirai"}, "2p": {"source": "ನಂಬಲು (2p future)", "target": "croirez"}, "2s": {"source": "ನಂಬಲು (2s future)", "target": "croiras"}, "3p": {"source": "ನಂಬಲು (3p future)", "target": "croiront"}, "3s": {"source": "ನಂಬಲು (3s future)", "target": "croira"}}, "pres": {"1p": {"source": "ನಂಬಲು (1p present)", "target": "croyons"}, "2p": {"source": "ನಂಬಲು (2p present)", "target": "croyez"}, "2s": {"source": "ನಂಬಲು (2s present)", "target": "crois"}, "3p": {"source": "ನಂಬಲು (3p present)", "target": "croient"}, "3s": {"source": "ನಂಬಲು (3s present)", "target": "croit"}}}},
    "tags": ["mental_state", "level_12"],
    "grammatical_forms": {
      "1p_future": {"level": 12, "target": "croirons", "english": "ನಂಬಲು (1p future)"},
      "1p_present": {"level": 12, "target": "croyons", "english": "ನಂಬಲು (1p present)"},
      "1s_future": {"level": 12, "target": "croirai", "english": "ನಂಬಲು (1s future)"},
      "2p_future": {"level": 12, "target": "croirez", "english": "ನಂಬಲು (2p future)"},
      "2p_present": {"level": 12, "target": "croyez", "english": "ನಂಬಲು (2p present)"},
      "2s_future": {"level": 12, "target": "croiras", "english": "ನಂಬಲು (2s future)"},
      "2s_present": {"level": 12, "target": "crois", "english": "ನಂಬಲು (2s present)"},
      "3p_future": {"level": 12, "target": "croiront", "english": "ನಂಬಲು (3p future)"},
      "3p_present": {"level": 12, "target": "croient", "english": "ನಂಬಲು (3p present)"},
      "3s_future": {"level": 12, "target": "croira", "english": "ನಂಬಲು (3s future)"},
      "3s_present": {"level": 12, "target": "croit", "english": "ನಂಬಲು (3s present)"}
    }
  },
  {
    "guid": "V04_033",
    "base_target": "décider",
    "base_source": "ನಿರ್ಧಾರಿಸು",
    "corpus": "VERBS",
    "group": "Mental State",
    "level": 12,
    "word_type": "verb",
    "conjugation_mode": {"format": "raw_forms_v2", "tables": {"fut": {"1p": {"source": "ನಿರ್ಧಾರಿಸು (1p future)", "target": "déciderons"}, "1s": {"source": "ನಿರ್ಧಾರಿಸು (1s future)", "target": "déciderai"}, "2p": {"source": "ನಿರ್ಧಾರಿಸು (2p future)", "target": "déciderez"}, "2s": {"source": "ನಿರ್ಧಾರಿಸು (2s future)", "target": "décideras"}, "3p": {"source": "ನಿರ್ಧಾರಿಸು (3p future)", "target": "décideront"}, "3s": {"source": "ನಿರ್ಧಾರಿಸು (3s future)", "target": "décidera"}}, "pres": {"1p": {"source": "ನಿರ್ಧಾರಿಸು (1p present)", "target": "décidons"}, "2p": {"source": "ನಿರ್ಧಾರಿಸು (2p present)", "target": "décidez"}, "2s": {"source": "ನಿರ್ಧಾರಿಸು (2s present)", "target": "décides"}, "3p": {"source": "ನಿರ್ಧಾರಿಸು (3p present)", "target": "décident"}, "3s": {"source": "ನಿರ್ಧಾರಿಸು (3s present)", "target": "décide"}}}},
    "tags": ["mental_state", "level_12"],
    "grammatical_forms": {
      "1p_future": {"level": 12, "target": "déciderons", "english": "ನಿರ್ಧಾರಿಸು (1p future)"},
      "1p_present": {"level": 12, "target": "décidons", "english": "ನಿರ್ಧಾರಿಸು (1p present)"},
      "1s_future": {"level": 12, "target": "déciderai", "english": "ನಿರ್ಧಾರಿಸು (1s future)"},
      "2p_future": {"level": 12, "target": "déciderez", "english": "ನಿರ್ಧಾರಿಸು (2p future)"},
      "2p_present": {"level": 12, "target": "décidez", "english": "ನಿರ್ಧಾರಿಸು (2p present)"},
      "2s_future": {"level": 12, "target": "décideras", "english": "ನಿರ್ಧಾರಿಸು (2s future)"},
      "2s_present": {"level": 12, "target": "décides", "english": "ನಿರ್ಧಾರಿಸು (2s present)"},
      "3p_future": {"level": 12, "target": "décideront", "english": "ನಿರ್ಧಾರಿಸು (3p future)"},
      "3p_present": {"level": 12, "target": "décident", "english": "ನಿರ್ಧಾರಿಸು (3p present)"},
      "3s_future": {"level": 12, "target": "décidera", "english": "ನಿರ್ಧಾರಿಸು (3s future)"},
      "3s_present": {"level": 12, "target": "décide", "english": "ನಿರ್ಧಾರಿಸು (3s present)"}
    }
  },
  {
    "guid": "V05_003",
    "base_target": "détester",
    "base_source": "ದ್ವೇಷಿಸು",
    "corpus": "VERBS",
    "group": "Emotional State",
    "level": 12,
    "word_type": "verb",
    "conjugation_mode": {"format": "raw_forms_v2", "tables": {"fut": {"1p": {"source": "ದ್ವೇಷಿಸು (1p future)", "target": "détesterons"}, "1s": {"source": "ದ್ವೇಷಿಸು (1s future)", "target": "détesterai"}, "2p": {"source": "ದ್ವೇಷಿಸು (2p future)", "target": "détesterez"}, "2s": {"source": "ದ್ವೇಷಿಸು (2s future)", "target": "détesteras"}, "3p": {"source": "ದ್ವೇಷಿಸು (3p future)", "target": "détesteront"}, "3s": {"source": "ದ್ವೇಷಿಸು (3s future)", "target": "détestera"}}, "pres": {"1p": {"source": "ದ್ವೇಷಿಸು (1p present)", "target": "détestons"}, "2p": {"source": "ದ್ವೇಷಿಸು (2p present)", "target": "détestez"}, "2s": {"source": "ದ್ವೇಷಿಸು (2s present)", "target": "détestes"}, "3p": {"source": "ದ್ವೇಷಿಸು (3p present)", "target": "détestent"}, "3s": {"source": "ದ್ವೇಷಿಸು (3s present)", "target": "déteste"}}}},
    "tags": ["emotional_state", "level_12"],
    "grammatical_forms": {
      "1p_future": {"level": 12, "target": "détesterons", "english": "ದ್ವೇಷಿಸು (1p future)"},
      "1p_present": {"level": 12, "target": "détestons", "english": "ದ್ವೇಷಿಸು (1p present)"},
      "1s_future": {"level": 12, "target": "détesterai", "english": "ದ್ವೇಷಿಸು (1s future)"},
      "2p_future": {"level": 12, "target": "détesterez", "english": "ದ್ವೇಷಿಸು (2p future)"},
      "2p_present": {"level": 12, "target": "détestez", "english": "ದ್ವೇಷಿಸು (2p present)"},
      "2s_future": {"level": 12, "target": "détesteras", "english": "ದ್ವೇಷಿಸು (2s future)"},
      "2s_present": {"level": 12, "target": "détestes", "english": "ದ್ವೇಷಿಸು (2s present)"},
      "3p_future": {"level": 12, "target": "détesteront", "english": "ದ್ವೇಷಿಸು (3p future)"},
      "3p_present": {"level": 12, "target": "détestent", "english": "ದ್ವೇಷಿಸು (3p present)"},
      "3s_future": {"level": 12, "target": "détestera", "english": "ದ್ವೇಷಿಸು (3s future)"},
      "3s_present": {"level": 12, "target": "déteste", "english": "ದ್ವೇಷಿಸು (3s present)"}
    }
  },
  {
    "guid": "V05_011",
    "base_target": "espérer",
    "base_source": "ಆಶಾವಹಿಸು",
    "corpus": "VERBS",
    "group": "Emotional State",
    "level": 12,
    "word_type": "verb",
    "conjugation_mode": {"format": "raw_forms_v2", "tables": {"fut": {"1p": {"source": "ಆಶಾವಹಿಸು (1p future)", "target": "espérerons"}, "1s": {"source": "ಆಶಾವಹಿಸು (1s future)", "target": "espérerai"}, "2p": {"source": "ಆಶಾವಹಿಸು (2p future)", "target": "espérerez"}, "2s": {"source": "ಆಶಾವಹಿಸು (2s future)", "target": "espéreras"}, "3p": {"source": "ಆಶಾವಹಿಸು (3p future)", "target": "espéreront"}, "3s": {"source": "ಆಶಾವಹಿಸು (3s future)", "target": "espérera"}}, "pres": {"1p": {"source": "ಆಶಾವಹಿಸು (1p present)", "target": "espérons"}, "2p": {"source": "ಆಶಾವಹಿಸು (2p present)", "target": "espérez"}, "2s": {"source": "ಆಶಾವಹಿಸು (2s present)", "target": "espéres"}, "3p": {"source": "ಆಶಾವಹಿಸು (3p present)", "target": "espérent"}, "3s": {"source": "ಆಶಾವಹಿಸು (3s present)", "target": "espére"}}}},
    "tags": ["emotional_state", "level_12"],
    "grammatical_forms": {
      "1p_future": {"level": 12, "target": "espérerons", "english": "ಆಶಾವಹಿಸು (1p future)"},
      "1p_present": {"level": 12, "target": "espérons", "english": "ಆಶಾವಹಿಸು (1p present)"},
      "1s_future": {"level": 12, "target": "espérerai", "english": "ಆಶಾವಹಿಸು (1s future)"},
      "2p_future": {"level": 12, "target": "espérerez", "english": "ಆಶಾವಹಿಸು (2p future)"},
      "2p_present": {"level": 12, "target": "espérez", "english": "ಆಶಾವಹಿಸು (2p present)"},
      "2s_future": {"level": 12, "target": "espéreras", "english": "ಆಶಾವಹಿಸು (2s future)"},
      "2s_present": {"level": 12, "target": "espéres", "english": "ಆಶಾವಹಿಸು (2s present)"},
      "3p_future": {"level": 12, "target": "espéreront", "english": "ಆಶಾವಹಿಸು (3p future)"},
      "3p_present": {"level": 12, "target": "espérent", "english": "ಆಶಾವಹಿಸು (3p present)"},
      "3s_future": {"level": 12, "target": "espérera", "english": "ಆಶಾವಹಿಸು (3s future)"},
      "3s_present": {"level": 12, "target": "espére", "english": "ಆಶಾವಹಿಸು (3s present)"}
    }
  },
  {
    "guid": "V09_002",
    "base_target": "parler",
    "base_source": "ಮಾತನಾಡು",
    "corpus": "VERBS",
    "group": "Communication",
    "level": 12,
    "word_type": "verb",
    "conjugation_mode": {"format": "raw_forms_v2", "tables": {"fut": {"1p": {"source": "ಮಾತನಾಡು (1p future)", "target": "parlerons"}, "1s": {"source": "ಮಾತನಾಡು (1s future)", "target": "parlerai"}, "2p": {"source": "ಮಾತನಾಡು (2p future)", "target": "parlerez"}, "2s": {"source": "ಮಾತನಾಡು (2s future)", "target": "parleras"}, "3p": {"source": "ಮಾತನಾಡು (3p future)", "target": "parleront"}, "3s": {"source": "ಮಾತನಾಡು (3s future)", "target": "parlera"}}, "pres": {"1p": {"source": "ಮಾತನಾಡು (1p present)", "target": "parlons"}, "2p": {"source": "ಮಾತನಾಡು (2p present)", "target": "parlez"}, "2s": {"source": "ಮಾತನಾಡು (2s present)", "target": "parles"}, "3p": {"source": "ಮಾತನಾಡು (3p present)", "target": "parlent"}, "3s": {"source": "ಮಾತನಾಡು (3s present)", "target": "parle"}}}},
    "tags": ["communication", "level_12"],
    "grammatical_forms": {
      "1p_future": {"level": 12, "target": "parlerons", "english": "ಮಾತನಾಡು (1p future)"},
      "1p_present": {"level": 12, "target": "parlons", "english": "ಮಾತನಾಡು (1p present)"},
      "1s_future": {"level": 12, "target": "parlerai", "english": "ಮಾತನಾಡು (1s future)"},
      "2p_future": {"level": 12, "target": "parlerez", "english": "ಮಾತನಾಡು (2p future)"},
      "2p_present": {"level": 12, "target": "parlez", "english": "ಮಾತನಾಡು (2p present)"},
      "2s_future": {"level": 12, "target": "parleras", "english": "ಮಾತನಾಡು (2s future)"},
      "2s_present": {"level": 12, "target": "parles", "english": "ಮಾತನಾಡು (2s present)"},
      "3p_future": {"level": 12, "target": "parleront", "english": "ಮಾತನಾಡು (3p future)"},
      "3p_present": {"level": 12, "target": "parlent", "english": "ಮಾತನಾಡು (3p present)"},
      "3s_future": {"level": 12, "target": "parlera", "english": "ಮಾತನಾಡು (3s future)"},
      "3s_present": {"level": 12, "target": "parle", "english": "ಮಾತನಾಡು (3s present)"}
    }
  },
  {
    "guid": "V09_005",
    "base_target": "répondre",
    "base_source": "ಉತ್ತರಿಸು",
    "corpus": "VERBS",
    "group": "Communication",
    "level": 12,
    "word_type": "verb",
    "conjugation_mode": {"format": "raw_forms_v2", "tables": {"fut": {"1p": {"source": "ಉತ್ತರಿಸು (1p future)", "target": "répondrons"}, "1s": {"source": "ಉತ್ತರಿಸು (1s future)", "target": "répondrai"}, "2p": {"source": "ಉತ್ತರಿಸು (2p future)", "target": "répondrez"}, "2s": {"source": "ಉತ್ತರಿಸು (2s future)", "target": "répondras"}, "3p": {"source": "ಉತ್ತರಿಸು (3p future)", "target": "répondront"}, "3s": {"source": "ಉತ್ತರಿಸು (3s future)", "target": "répondra"}}, "pres": {"1p": {"source": "ಉತ್ತರಿಸು (1p present)", "target": "répondons"}, "2p": {"source": "ಉತ್ತರಿಸು (2p present)", "target": "répondez"}, "2s": {"source": "ಉತ್ತರಿಸು (2s present)", "target": "réponds"}, "3p": {"source": "ಉತ್ತರಿಸು (3p present)", "target": "répondent"}, "3s": {"source": "ಉತ್ತರಿಸು (3s present)", "target": "répond"}}}},
    "tags": ["communication", "level_12"],
    "grammatical_forms": {
      "1p_future": {"level": 12, "target": "répondrons", "english": "ಉತ್ತರಿಸು (1p future)"},
      "1p_present": {"level": 12, "target": "répondons", "english": "ಉತ್ತರಿಸು (1p present)"},
      "1s_future": {"level": 12, "target": "répondrai", "english": "ಉತ್ತರಿಸು (1s future)"},
      "2p_future": {"level": 12, "target": "répondrez", "english": "ಉತ್ತರಿಸು (2p future)"},
      "2p_present": {"level": 12, "target": "répondez", "english": "ಉತ್ತರಿಸು (2p present)"},
      "2s_future": {"level": 12, "target": "répondras", "english": "ಉತ್ತರಿಸು (2s future)"},
      "2s_present": {"level": 12, "target": "réponds", "english": "ಉತ್ತರಿಸು (2s present)"},
      "3p_future": {"level": 12, "target": "répondront", "english": "ಉತ್ತರಿಸು (3p future)"},
      "3p_present": {"level": 12, "target": "répondent", "english": "ಉತ್ತರಿಸು (3p present)"},
      "3s_future": {"level": 12, "target": "répondra", "english": "ಉತ್ತರಿಸು (3s future)"},
      "3s_present": {"level": 12, "target": "répond", "english": "ಉತ್ತರಿಸು (3s present)"}
    }
  },
  {
    "guid": "V12_007",
    "base_target": "partir",
    "base_source": "ನಿರ್ಗಮಿಸು",
    "corpus": "VERBS",
    "group": "Directional Movement",
    "level": 12,
    "word_type": "verb",
    "conjugation_mode": {"format": "raw_forms_v2", "tables": {"fut": {"1p": {"source": "ನಿರ್ಗಮಿಸು (1p future)", "target": "partirons"}, "1s": {"source": "ನಿರ್ಗಮಿಸು (1s future)", "target": "partirai"}, "2p": {"source": "ನಿರ್ಗಮಿಸು (2p future)", "target": "partirez"}, "2s": {"source": "ನಿರ್ಗಮಿಸು (2s future)", "target": "partiras"}, "3p": {"source": "ನಿರ್ಗಮಿಸು (3p future)", "target": "partiront"}, "3s": {"source": "ನಿರ್ಗಮಿಸು (3s future)", "target": "partira"}}, "pres": {"1p": {"source": "ನಿರ್ಗಮಿಸು (1p present)", "target": "partons"}, "2p": {"source": "ನಿರ್ಗಮಿಸು (2p present)", "target": "partez"}, "2s": {"source": "ನಿರ್ಗಮಿಸು (2s present)", "target": "pars"}, "3p": {"source": "ನಿರ್ಗಮಿಸು (3p present)", "target": "partent"}, "3s": {"source": "ನಿರ್ಗಮಿಸು (3s present)", "target": "part"}}}},
    "tags": ["directional_movement", "level_12"],
    "grammatical_forms": {
      "1p_future": {"level": 12, "target": "partirons", "english": "ನಿರ್ಗಮಿಸು (1p future)"},
      "1p_present": {"level": 12, "target": "partons", "english": "ನಿರ್ಗಮಿಸು (1p present)"},
      "1s_future": {"level": 12, "target": "partirai", "english": "ನಿರ್ಗಮಿಸು (1s future)"},
      "2p_future": {"level": 12, "target": "partirez", "english": "ನಿರ್ಗಮಿಸು (2p future)"},
      "2p_present": {"level": 12, "target": "partez", "english": "ನಿರ್ಗಮಿಸು (2p present)"},
      "2s_future": {"level": 12, "target": "partiras", "english": "ನಿರ್ಗಮಿಸು (2s future)"},
      "2s_present": {"level": 12, "target": "pars", "english": "ನಿರ್ಗಮಿಸು (2s present)"},
      "3p_future": {"level": 12, "target": "partiront", "english": "ನಿರ್ಗಮಿಸು (3p future)"},
      "3p_present": {"level": 12, "target": "partent", "english": "ನಿರ್ಗಮಿಸು (3p present)"},
      "3s_future": {"level": 12, "target": "partira", "english": "ನಿರ್ಗಮಿಸು (3s future)"},
      "3s_present": {"level": 12, "target": "part", "english": "ನಿರ್ಗಮಿಸು (3s present)"}
    }
  },
  {"guid": "A05_035", "base_target": "nouveau", "base_source": "ಹೊಸ", "corpus": "WORDS4", "group": "Quality", "level": 13, "word_type": "adjective", "tags": ["quality", "level_13"]},
  {"guid": "A05_036", "base_target": "important", "base_source": "ಪ್ರಮುಖ", "corpus": "WORDS4", "group": "Quality", "level": 13, "word_type": "adjective", "tags": ["quality", "level_13"]},
  {"guid": "A05_037", "base_target": "nécessaire", "base_source": "ಅವಶ್ಯಕ", "corpus": "WORDS4", "group": "Quality", "level": 13, "word_type": "adjective", "tags": ["quality", "level_13"]},
  {"guid": "A05_038", "base_target": "possible", "base_source": "ಸಾಧ್ಯ", "corpus": "WORDS4", "group": "Quality", "level": 13, "word_type": "adjective", "tags": ["quality", "level_13"]},
  {"guid": "A05_039", "base_target": "impossible", "base_source": "ಅಸಾಧ್ಯ", "corpus": "WORDS4", "group": "Quality", "level": 13, "word_type": "adjective", "tags": ["quality", "level_13"]},
  {"guid": "A05_040", "base_target": "réel", "base_source": "ವಾಸ್ತವ", "corpus": "WORDS4", "group": "Quality", "level": 13, "word_type": "adjective", "tags": ["quality", "level_13"]},
  {"guid": "A05_041", "base_target": "clair", "base_source": "ಸ್ಪಷ್ಟ", "corpus": "WORDS4", "group": "Quality", "level": 13, "word_type": "adjective", "tags": ["quality", "level_13"]},
  {"guid": "A05_042", "base_target": "simple", "base_source": "ಸರಳ", "corpus": "WORDS4", "group": "Quality", "level": 13, "word_type": "adjective", "tags": ["quality", "level_13"]},
  {"guid": "A05_043", "base_target": "correct", "base_source": "ಸರಿ", "corpus": "WORDS4", "group": "Quality", "level": 13, "word_type": "adjective", "tags": ["quality", "level_13"]},
  {"guid": "A05_044", "base_target": "faux", "base_source": "ತಪ್ಪು", "corpus": "WORDS4", "group": "Quality", "level": 13, "word_type": "adjective", "tags": ["quality", "level_13"]},
  {"guid": "A05_045", "base_target": "libre", "base_source": "ಸ್ವತಂತ್ರ", "corpus": "WORDS4", "group": "Quality", "level": 13, "word_type": "adjective", "tags": ["quality", "level_13"]},
  {"guid": "A05_046", "base_target": "plein", "base_source": "ಪೂರ್ಣ", "corpus": "WORDS4", "group": "Quality", "level": 13, "word_type": "adjective", "tags": ["quality", "level_13"]},
  {"guid": "A05_047", "base_target": "vide", "base_source": "ಖಾಲಿ", "corpus": "WORDS4", "group": "Quality", "level": 13, "word_type": "adjective", "tags": ["quality", "level_13"]},
  {"guid": "N25_001", "base_target": "vie", "base_source": "ಜೀವನ", "corpus": "WORDS4", "group": "Time Period", "level": 13, "word_type": "noun", "tags": ["time_period", "level_13"]},
  {"guid": "N25_002", "base_target": "jour", "base_source": "ದಿನ", "corpus": "WORDS4", "group": "Time Period", "level": 13, "word_type": "noun", "tags": ["time_period", "level_13"]},
  {"guid": "N25_003", "base_target": "nuit", "base_source": "ರಾತ್ರಿ", "corpus": "WORDS4", "group": "Time Period", "level": 13, "word_type": "noun", "tags": ["time_period", "level_13"]},
  {"guid": "N25_004", "base_target": "matin", "base_source": "ಬೆಳಗ್ಗೆ", "corpus": "WORDS4", "group": "Time Period", "level": 13, "word_type": "noun", "tags": ["time_period", "level_13"]},
  {"guid": "N25_005", "base_target": "soir", "base_source": "ಸಂಜೆ", "corpus": "WORDS4", "group": "Time Period", "level": 13, "word_type": "noun", "tags": ["time_period", "level_13"]},
  {"guid": "N25_006", "base_target": "décennie", "base_source": "ದಶಕ", "corpus": "WORDS4", "group": "Time Period", "level": 13, "word_type": "noun", "tags": ["time_period", "level_13"]},
  {"guid": "N25_007", "base_target": "année", "base_source": "ವರ್ಷ", "corpus": "WORDS4", "group": "Time Period", "level": 13, "word_type": "noun", "tags": ["time_period", "level_13"]},
  {"guid": "N25_008", "base_target": "mois", "base_source": "ತಿಂಗಳು", "corpus": "WORDS4", "group": "Time Period", "level": 13, "word_type": "noun", "tags": ["time_period", "level_13"]},
  {"guid": "N25_009", "base_target": "semaine", "base_source": "ವಾರ", "corpus": "WORDS4", "group": "Time Period", "level": 13, "word_type": "noun", "tags": ["time_period", "level_13"]},
  {"guid": "N25_010", "base_target": "heure", "base_source": "ಗಂಟೆ", "corpus": "WORDS4", "group": "Time Period", "level": 13, "word_type": "noun", "tags": ["time_period", "level_13"]},
  {"guid": "N25_011", "base_target": "minute", "base_source": "ನಿಮಿಷ", "corpus": "WORDS4", "group": "Time Period", "level": 13, "word_type": "noun", "tags": ["time_period", "level_13"]},
  {"guid": "N25_012", "base_target": "moment", "base_source": "ಕ್ಷಣ", "corpus": "WORDS4", "group": "Time Period", "level": 13, "word_type": "noun", "tags": ["time_period", "level_13"]},
  {"guid": "N25_013", "base_target": "mort", "base_source": "ಮರಣ", "corpus": "WORDS4", "group": "Time Period", "level": 13, "word_type": "noun", "tags": ["time_period", "level_13"]},
  {"guid": "N25_020", "base_target": "passé", "base_source": "ಭೂತಕಾಲ", "corpus": "WORDS4", "group": "Time Period", "level": 13, "word_type": "noun", "tags": ["time_period", "level_13"]},
  {"guid": "N30_036", "base_target": "lieu", "base_source": "ಸ್ಥಳ", "corpus": "WORDS4", "group": "Place Name", "level": 13, "word_type": "noun", "tags": ["place_name", "level_13"]},
  {"guid": "N30_039", "base_target": "ville", "base_source": "ನಗರ", "corpus": "WORDS4", "group": "Place Name", "level": 13, "word_type": "noun", "tags": ["place_name", "level_13"]},
  {"guid": "N30_040", "base_target": "pays", "base_source": "దేశ", "corpus": "WORDS4", "group": "Place Name", "level": 13, "word_type": "noun", "tags": ["place_name", "level_13"]},
  {"guid": "N30_041", "base_target": "état", "base_source": "ರಾಜ್ಯ", "corpus": "WORDS4", "group": "Place Name", "level": 13, "word_type": "noun", "tags": ["place_name", "level_13"]},
  {"guid": "N30_042", "base_target": "zone", "base_source": "ಪ್ರದೇಶ", "corpus": "WORDS4", "group": "Place Name", "level": 13, "word_type": "noun", "tags": ["place_name", "level_13"]},
  {"guid": "N30_043", "base_target": "terre", "base_source": "ಭೂಮಿ", "corpus": "WORDS4", "group": "Place Name", "level": 13, "word_type": "noun", "tags": ["place_name", "level_13"]},
  {"guid": "N30_047", "base_target": "nord", "base_source": "ಉತ್ತರ", "corpus": "WORDS4", "group": "Place Name", "level": 13, "word_type": "noun", "tags": ["place_name", "level_13"]},
  {"guid": "N30_048", "base_target": "sud", "base_source": "ದಕ್ಷಿಣ", "corpus": "WORDS4", "group": "Place Name", "level": 13, "word_type": "noun", "tags": ["place_name", "level_13"]},
  {"guid": "N30_049", "base_target": "est", "base_source": "ಪೂರ್ವ", "corpus": "WORDS4", "group": "Place Name", "level": 13, "word_type": "noun", "tags": ["place_name", "level_13"]},
  {"guid": "N30_050", "base_target": "ouest", "base_source": "ಪಶ್ಚಿಮ", "corpus": "WORDS4", "group": "Place Name", "level": 13, "word_type": "noun", "tags": ["place_name", "level_13"]},
  {"guid": "N30_051", "base_target": "intérieur", "base_source": "ಒಳಭಾಗ", "corpus": "WORDS4", "group": "Place Name", "level": 13, "word_type": "noun", "tags": ["place_name", "level_13"]},
  {"guid": "N30_052", "base_target": "extérieur", "base_source": "ಬಾಹ್ಯ ಭಾಗ", "corpus": "WORDS4", "group": "Place Name", "level": 13, "word_type": "noun", "tags": ["place_name", "level_13"]},
  {"guid": "N30_053", "base_target": "derrière", "base_source": "ಹಿನ್ನೆಲೆ", "corpus": "WORDS4", "group": "Place Name", "level": 13, "word_type": "noun", "tags": ["place_name", "level_13"]},
  {"guid": "N33_009", "base_target": "Russe", "base_source": "ರಷ್ಯಾನಿಗ", "corpus": "WORDS4", "group": "Nationality", "level": 13, "word_type": "noun", "tags": ["nationality", "level_13"]},
  {"guid": "N41_001", "base_target": "lecture", "base_source": "ಓದುವಿಕೆ", "corpus": "WORDS4", "group": "Activity", "level": 13, "word_type": "noun", "tags": ["activity", "level_13"]},
  {"guid": "N41_002", "base_target": "écriture", "base_source": "ಲೇಖನ", "corpus": "WORDS4", "group": "Activity", "level": 13, "word_type": "noun", "tags": ["activity", "level_13"]},
  {"guid": "N41_003", "base_target": "dessin", "base_source": "ರೇಖಾಚಿತ್ರ", "corpus": "WORDS4", "group": "Activity", "level": 13, "word_type": "noun", "tags": ["activity", "level_13"]},
  {"guid": "N41_004", "base_target": "peinture", "base_source": "ಚಿತ್ರಕಲೆ", "corpus": "WORDS4", "group": "Activity", "level": 13, "word_type": "noun", "tags": ["activity", "level_13"]},
  {"guid": "N41_005", "base_target": "chant", "base_source": "ಹಾಡುವುದು", "corpus": "WORDS4", "group": "Activity", "level": 13, "word_type": "noun", "tags": ["activity", "level_13"]},
  {"guid": "N41_006", "base_target": "danse", "base_source": "ನೃತ್ಯ", "corpus": "WORDS4", "group": "Activity", "level": 13, "word_type": "noun", "tags": ["activity", "level_13"]},
  {"guid": "N41_007", "base_target": "cuisine", "base_source": "ಅಡುಗೆ", "corpus": "WORDS4", "group": "Activity", "level": 13, "word_type": "noun", "tags": ["activity", "level_13"]},
  {"guid": "N41_008", "base_target": "pâtisserie", "base_source": "ಒವನ್‌ಬೇಕ್‌ ಮಾಡುವುದು", "corpus": "WORDS4", "group": "Activity", "level": 13, "word_type": "noun", "tags": ["activity", "level_13"]},
  {"guid": "N41_009", "base_target": "jardinage", "base_source": "ತೋಟಗಾರಿಕೆ", "corpus": "WORDS4", "group": "Activity", "level": 13, "word_type": "noun", "tags": ["activity", "level_13"]},
  {"guid": "N41_010", "base_target": "pêche", "base_source": "ಮೀನುಗಾರಿಕೆ", "corpus": "WORDS4", "group": "Activity", "level": 13, "word_type": "noun", "tags": ["activity", "level_13"]},
  {"guid": "N41_011", "base_target": "randonnée", "base_source": "ಹೈಕಿಂಗ್", "corpus": "WORDS4", "group": "Activity", "level": 13, "word_type": "noun", "tags": ["activity", "level_13"]},
  {"guid": "N41_012", "base_target": "camping", "base_source": "ಕ್ಯಾಂಪಿಂಗ್", "corpus": "WORDS4", "group": "Activity", "level": 13, "word_type": "noun", "tags": ["activity", "level_13"]},
  {"guid": "N41_013", "base_target": "voyage", "base_source": "ಪ್ರಯಾಣ", "corpus": "WORDS4", "group": "Activity", "level": 13, "word_type": "noun", "tags": ["activity", "level_13"]},
  {"guid": "N41_014", "base_target": "photographie", "base_source": "ಫೋಟೋಗ್ರಫಿ", "corpus": "WORDS4", "group": "Activity", "level": 13, "word_type": "noun", "tags": ["activity", "level_13"]},
  {"guid": "N41_015", "base_target": "sport", "base_source": "ಕ್ರೀಡೆ", "corpus": "WORDS4", "group": "Activity", "level": 13, "word_type": "noun", "tags": ["activity", "level_13"]},
  {"guid": "N41_016", "base_target": "musique", "base_source": "ಸಂಗೀತ", "corpus": "WORDS4", "group": "Activity", "level": 13, "word_type": "noun", "tags": ["activity", "level_13"]},
  {"guid": "N41_017", "base_target": "film", "base_source": "ಚಲನಚಿತ್ರ", "corpus": "WORDS4", "group": "Activity", "level": 13, "word_type": "noun", "tags": ["activity", "level_13"]},
  {"guid": "N41_018", "base_target": "jeu", "base_source": "ಆಟ", "corpus": "WORDS4", "group": "Activity", "level": 13, "word_type": "noun", "tags": ["activity", "level_13"]},
  {"guid": "N45_004", "base_target": "Pologne", "base_source": "ಪೋಲೆಂಡ್", "corpus": "WORDS4", "group": "Country", "level": 13, "word_type": "noun", "tags": ["country", "level_13"]},
  {"guid": "N45_009", "base_target": "Russie", "base_source": "ರಷ್ಯಾ", "corpus": "WORDS4", "group": "Country", "level": 13, "word_type": "noun", "tags": ["country", "level_13"]},
  {"guid": "N45_013", "base_target": "Japon", "base_source": "ಜಪಾನ್", "corpus": "WORDS4", "group": "Country", "level": 13, "word_type": "noun", "tags": ["country", "level_13"]},
  {"guid": "N45_014", "base_target": "Chine", "base_source": "ಚೀನಾ", "corpus": "WORDS4", "group": "Country", "level": 13, "word_type": "noun", "tags": ["country", "level_13"]},
  {"guid": "N45_015", "base_target": "Inde", "base_source": "ಭಾರತ", "corpus": "WORDS4", "group": "Country", "level": 13, "word_type": "noun", "tags": ["country", "level_13"]},
  {"guid": "N45_016", "base_target": "Brésil", "base_source": "ಬ್ರೆಜಿಲ್", "corpus": "WORDS4", "group": "Country", "level": 13, "word_type": "noun", "tags": ["country", "level_13"]},
  {"guid": "A18_014", "base_target": "lourd", "base_source": "ಭಾರವಾದ", "corpus": "WORDS4", "group": "Physical Property", "level": 14, "word_type": "adjective", "tags": ["physical_property", "level_14"]},
  {"guid": "A18_015", "base_target": "grand", "base_source": "ಎತ್ತರದ", "corpus": "WORDS4", "group": "Physical Property", "level": 14, "word_type": "adjective", "tags": ["physical_property", "level_14"]},
  {"guid": "A18_016", "base_target": "rapide", "base_source": "ವೇಗವಾದ", "corpus": "WORDS4", "group": "Physical Property", "level": 14, "word_type": "adjective", "tags": ["physical_property", "level_14"]},
  {"guid": "A18_018", "base_target": "brillant", "base_source": "ಪ್ರಕಾಶಮಾನ", "corpus": "WORDS4", "group": "Physical Property", "level": 14, "word_type": "adjective", "tags": ["physical_property", "level_14"]},
  {"guid": "A18_027", "base_target": "propre", "base_source": "ಶುಚಿಯಾದ", "corpus": "WORDS4", "group": "Physical Property", "level": 14, "word_type": "adjective", "tags": ["physical_property", "level_14"]},
  {"guid": "A18_029", "base_target": "fort", "base_source": "ಜೋರಾದ", "corpus": "WORDS4", "group": "Physical Property", "level": 14, "word_type": "adjective", "tags": ["physical_property", "level_14"]},
  {"guid": "A18_036", "base_target": "lisse", "base_source": "ನಯವಾದ", "corpus": "WORDS4", "group": "Physical Property", "level": 14, "word_type": "adjective", "tags": ["physical_property", "level_14"]},
  {"guid": "A18_046", "base_target": "léger", "base_source": "ಹಗುರವಾದ", "corpus": "WORDS4", "group": "Physical Property", "level": 14, "word_type": "adjective", "tags": ["physical_property", "level_14"]},
  {"guid": "A18_060", "base_target": "tranchant", "base_source": "ಹರಿತವಾದ", "corpus": "WORDS4", "group": "Physical Property", "level": 14, "word_type": "adjective", "tags": ["physical_property", "level_14"]},
  {"guid": "A18_062", "base_target": "mince", "base_source": "ತೆಳುವಾದ", "corpus": "WORDS4", "group": "Physical Property", "level": 14, "word_type": "adjective", "tags": ["physical_property", "level_14"]},
  {"guid": "A18_063", "base_target": "doux", "base_source": "ಮೃದುವಾದ", "corpus": "WORDS4", "group": "Physical Property", "level": 14, "word_type": "adjective", "tags": ["physical_property", "level_14"]},
  {"guid": "A18_067", "base_target": "lent", "base_source": "ನಿಧಾನ", "corpus": "WORDS4", "group": "Physical Property", "level": 14, "word_type": "adjective", "tags": ["physical_property", "level_14"]},
  {"guid": "A18_068", "base_target": "calme", "base_source": "ಶಾಂತ", "corpus": "WORDS4", "group": "Physical Property", "level": 14, "word_type": "adjective", "tags": ["physical_property", "level_14"]},
  {"guid": "A18_069", "base_target": "dur", "base_source": "ಗಟ್ಟಿಯಾದ", "corpus": "WORDS4", "group": "Physical Property", "level": 14, "word_type": "adjective", "tags": ["physical_property", "level_14"]},
  {"guid": "A18_070", "base_target": "sale", "base_source": "ಕೊಳಕು", "corpus": "WORDS4", "group": "Physical Property", "level": 14, "word_type": "adjective", "tags": ["physical_property", "level_14"]},
  {"guid": "A18_071", "base_target": "rugueux", "base_source": "ಒರಟಾದ", "corpus": "WORDS4", "group": "Physical Property", "level": 14, "word_type": "adjective", "tags": ["physical_property", "level_14"]},
  {"guid": "N11_020", "base_target": "ciel", "base_source": "ಆಕಾಶ", "corpus": "WORDS4", "group": "Natural Feature", "level": 14, "word_type": "noun", "tags": ["natural_feature", "level_14"]},
  {"guid": "N11_021", "base_target": "soleil", "base_source": "ಸೂರ್ಯ", "corpus": "WORDS4", "group": "Natural Feature", "level": 14, "word_type": "noun", "tags": ["natural_feature", "level_14"]},
  {"guid": "N11_022", "base_target": "lune", "base_source": "ಚಂದ್ರ", "corpus": "WORDS4", "group": "Natural Feature", "level": 14, "word_type": "noun", "tags": ["natural_feature", "level_14"]},
  {"guid": "N11_023", "base_target": "étoile", "base_source": "ನಕ್ಷತ್ರ", "corpus": "WORDS4", "group": "Natural Feature", "level": 14, "word_type": "noun", "tags": ["natural_feature", "level_14"]},
  {"guid": "N11_024", "base_target": "nuage", "base_source": "ಮೋಡ", "corpus": "WORDS4", "group": "Natural Feature", "level": 14, "word_type": "noun", "tags": ["natural_feature", "level_14"]},
  {"guid": "N11_025", "base_target": "pluie", "base_source": "ಮಳೆ", "corpus": "WORDS4", "group": "Natural Feature", "level": 14, "word_type": "noun", "tags": ["natural_feature", "level_14"]},
  {"guid": "N11_026", "base_target": "neige", "base_source": "ಹಿಮ", "corpus": "WORDS4", "group": "Natural Feature", "level": 14, "word_type": "noun", "tags": ["natural_feature", "level_14"]},
  {"guid": "N11_027", "base_target": "vent", "base_source": "ಗಾಳಿ", "corpus": "WORDS4", "group": "Natural Feature", "level": 14, "word_type": "noun", "tags": ["natural_feature", "level_14"]},
  {"guid": "N11_028", "base_target": "tempête", "base_source": "ಬಿರುಗಾಳಿ", "corpus": "WORDS4", "group": "Natural Feature", "level": 14, "word_type": "noun", "tags": ["natural_feature", "level_14"]},
  {"guid": "N11_029", "base_target": "brouillard", "base_source": "ಮಂಜು", "corpus": "WORDS4", "group": "Natural Feature", "level": 14, "word_type": "noun", "tags": ["natural_feature", "level_14"]},
  {"guid": "N11_030", "base_target": "glace", "base_source": "ಮಂಜುಗಡ್ಡೆ", "corpus": "WORDS4", "group": "Natural Feature", "level": 14, "word_type": "noun", "tags": ["natural_feature", "level_14"]},
  {"guid": "N11_031", "base_target": "température", "base_source": "ತಾಪಮಾನ", "corpus": "WORDS4", "group": "Natural Feature", "level": 14, "word_type": "noun", "tags": ["natural_feature", "level_14"]},
  {"guid": "N32_020", "base_target": "Noël", "base_source": "ಕ್ರಿಸ್‌ಮಸ್", "corpus": "WORDS4", "group": "Temporal Name", "level": 14, "word_type": "noun", "tags": ["temporal_name", "level_14"]},
  {"guid": "N32_021", "base_target": "Pâques", "base_source": "ಈಸ್ಟರ್", "corpus": "WORDS4", "group": "Temporal Name", "level": 14, "word_type": "noun", "tags": ["temporal_name", "level_14"]},
  {"guid": "N33_004", "base_target": "Polonais", "base_source": "ಪೋಲಿಷ್", "corpus": "WORDS5", "group": "Nationality", "level": 14, "word_type": "noun", "tags": ["nationality", "level_14"]},
  {"guid": "N33_006", "base_target": "Français", "base_source": "ಫ್ರೆಂಚ್‌ವ್ಯಕ್ತಿ", "corpus": "WORDS5", "group": "Nationality", "level": 14, "word_type": "noun", "tags": ["nationality", "level_14"]},
  {"guid": "N33_007", "base_target": "Espagnol", "base_source": "ಸ್ಪ್ಯಾನಿಯನ್", "corpus": "WORDS5", "group": "Nationality", "level": 14, "word_type": "noun", "tags": ["nationality", "level_14"]},
  {"guid": "N33_010", "base_target": "Anglais", "base_source": "ಇಂಗ್ಲಿಷ್‌ಮ್ಯಾನ್", "corpus": "WORDS5", "group": "Nationality", "level": 14, "word_type": "noun", "tags": ["nationality", "level_14"]},
  {"guid": "N33_013", "base_target": "Japonais", "base_source": "ಜಪಾನಿ", "corpus": "WORDS5", "group": "Nationality", "level": 14, "word_type": "noun", "tags": ["nationality", "level_14"]},
  {"guid": "N33_014", "base_target": "Chinois", "base_source": "ಚೀನೀ", "corpus": "WORDS5", "group": "Nationality", "level": 14, "word_type": "noun", "tags": ["nationality", "level_14"]},
  {"guid": "N33_015", "base_target": "Suédois", "base_source": "ಸ್ವೀಡಿಷ್ ಜನ", "corpus": "WORDS5", "group": "Nationality", "level": 14, "word_type": "noun", "tags": ["nationality", "level_14"]},
  {"guid": "N33_017", "base_target": "Finlandais", "base_source": "ಫಿನ್ನ್", "corpus": "WORDS5", "group": "Nationality", "level": 14, "word_type": "noun", "tags": ["nationality", "level_14"]},
  {"guid": "N46_001", "base_target": "Varsovie", "base_source": "ವಾರ್ಸಾ", "corpus": "WORDS4", "group": "City", "level": 14, "word_type": "noun", "tags": ["city", "level_14"]},
  {"guid": "N46_002", "base_target": "Berlin", "base_source": "ಬೆರ್ಲಿನ್", "corpus": "WORDS4", "group": "City", "level": 14, "word_type": "noun", "tags": ["city", "level_14"]},
  {"guid": "N46_003", "base_target": "Paris", "base_source": "ಪ್ಯಾರಿಸ್", "corpus": "WORDS4", "group": "City", "level": 14, "word_type": "noun", "tags": ["city", "level_14"]},
  {"guid": "N46_004", "base_target": "Londres", "base_source": "ಲಂಡನ್", "corpus": "WORDS4", "group": "City", "level": 14, "word_type": "noun", "tags": ["city", "level_14"]},
  {"guid": "N46_005", "base_target": "Rome", "base_source": "ರೋಮ್", "corpus": "WORDS4", "group": "City", "level": 14, "word_type": "noun", "tags": ["city", "level_14"]},
  {"guid": "N46_006", "base_target": "Madrid", "base_source": "ಮ್ಯಾಡ್ರಿಡ್", "corpus": "WORDS4", "group": "City", "level": 14, "word_type": "noun", "tags": ["city", "level_14"]},
  {"guid": "N46_007", "base_target": "Moscou", "base_source": "ಮಾಸ್ಕೋ", "corpus": "WORDS4", "group": "City", "level": 14, "word_type": "noun", "tags": ["city", "level_14"]},
  {"guid": "N46_008", "base_target": "New York", "base_source": "ನ್ಯೂಯಾರ್ಕ್", "corpus": "WORDS4", "group": "City", "level": 14, "word_type": "noun", "tags": ["city", "level_14"]},
  {"guid": "N46_009", "base_target": "Chicago", "base_source": "ಶಿಕಾಗೋ", "corpus": "WORDS4", "group": "City", "level": 14, "word_type": "noun", "tags": ["city", "level_14"]},
  {"guid": "N46_010", "base_target": "Los Angeles", "base_source": "ಲಾಸ್ ಏಂಜೆಲಿಸ್", "corpus": "WORDS4", "group": "City", "level": 14, "word_type": "noun", "tags": ["city", "level_14"]},
  {"guid": "N46_011", "base_target": "Tokyo", "base_source": "ಟೋಕಿಯೋ", "corpus": "WORDS4", "group": "City", "level": 14, "word_type": "noun", "tags": ["city", "level_14"]},
  {"guid": "N46_012", "base_target": "Pékin", "base_source": "ಬೈಜಿಂಗ್", "corpus": "WORDS4", "group": "City", "level": 14, "word_type": "noun", "tags": ["city", "level_14"]},
  {"guid": "N46_013", "base_target": "Stockholm", "base_source": "ಸ್ಟಾಕ್‌ಹೋಲ್ಮ್", "corpus": "WORDS4", "group": "City", "level": 14, "word_type": "noun", "tags": ["city", "level_14"]},
  {"guid": "N46_014", "base_target": "Oslo", "base_source": "ಒಸ್ಲೋ", "corpus": "WORDS4", "group": "City", "level": 14, "word_type": "noun", "tags": ["city", "level_14"]},
  {"guid": "N46_015", "base_target": "Helsinki", "base_source": "ಹೆಲ್ಸಿಂಕಿ", "corpus": "WORDS4", "group": "City", "level": 14, "word_type": "noun", "tags": ["city", "level_14"]},
  {"guid": "N02_017", "base_target": "hibou", "base_source": "ಹುಲಿಯಕ್ಕಿ", "corpus": "WORDS3", "group": "Animals", "level": 15, "word_type": "noun", "tags": ["animal", "level_15"]},
  {"guid": "N02_018", "base_target": "araignée", "base_source": "ಒಣಚಿಲುಟ", "corpus": "WORDS3", "group": "Animals", "level": 15, "word_type": "noun", "tags": ["animal", "level_15"]},
  {"guid": "N02_019", "base_target": "écureuil", "base_source": "ಗಿಳಿಗೆಂದನು", "corpus": "WORDS3", "group": "Animals", "level": 15, "word_type": "noun", "tags": ["animal", "level_15"]},
  {"guid": "N02_020", "base_target": "chèvre", "base_source": "ಮೇಕೆ", "corpus": "WORDS3", "group": "Animals", "level": 15, "word_type": "noun", "tags": ["animal", "level_15"]},
  {"guid": "N02_021", "base_target": "oie", "base_source": "ಹದ್ದು", "corpus": "WORDS3", "group": "Animals", "level": 15, "word_type": "noun", "tags": ["animal", "level_15"]},
  {"guid": "N02_022", "base_target": "canard", "base_source": "ಬೆಕ್ಕೆಗೋಲು (ಬೆಕ್ಕೆಗೋಲು is incorrect)", "corpus": "WORDS3", "group": "Animals", "level": 15, "word_type": "noun", "tags": ["animal", "level_15"]},
  {"guid": "N02_023", "base_target": "grenouille", "base_source": "ದೊಂಡೆಮರಿ", "corpus": "WORDS3", "group": "Animals", "level": 15, "word_type": "noun", "tags": ["animal", "level_15"]},
  {"guid": "N02_024", "base_target": "papillon", "base_source": "ಚಿಟ್ಟೆ", "corpus": "WORDS3", "group": "Animals", "level": 15, "word_type": "noun", "tags": ["animal", "level_15"]},
  {"guid": "N02_025", "base_target": "tortue", "base_source": "ಗಿದೆ", "corpus": "WORDS3", "group": "Animals", "level": 15, "word_type": "noun", "tags": ["animal", "level_15"]},
  {"guid": "N02_026", "base_target": "corneille", "base_source": "ಕರಡಿ ತಾರಕ (ಕಾಗೆ)", "corpus": "WORDS3", "group": "Animals", "level": 15, "word_type": "noun", "tags": ["animal", "level_15"]},
  {"guid": "N02_027", "base_target": "aigle", "base_source": "ಗರುಡ", "corpus": "WORDS3", "group": "Animals", "level": 15, "word_type": "noun", "tags": ["animal", "level_15"]},
  {"guid": "N02_028", "base_target": "mouton", "base_source": "मेंಕ (transliteration not allowed?)", "corpus": "WORDS3", "group": "Animals", "level": 15, "word_type": "noun", "tags": ["animal", "level_15"]},
  {"guid": "N03_031", "base_target": "poumon", "base_source": "ಫೆಫಸೆ", "corpus": "WORDS3", "group": "Body Part", "level": 15, "word_type": "noun", "tags": ["body_part", "level_15"]},
  {"guid": "N03_032", "base_target": "cerveau", "base_source": "ಮಗಜ", "corpus": "WORDS3", "group": "Body Part", "level": 15, "word_type": "noun", "tags": ["body_part", "level_15"]},
  {"guid": "N03_033", "base_target": "rein", "base_source": "ಮೂತ್ರದಂಡೆ", "corpus": "WORDS3", "group": "Body Part", "level": 15, "word_type": "noun", "tags": ["body_part", "level_15"]},
  {"guid": "N03_034", "base_target": "sang", "base_source": "ರಕ್ತ", "corpus": "WORDS3", "group": "Body Part", "level": 15, "word_type": "noun", "tags": ["body_part", "level_15"]},
  {"guid": "N03_035", "base_target": "colonne vertébrale", "base_source": "ಉತ್ತೇಜನ ಕಾಲರವಳಿ", "corpus": "WORDS3", "group": "Body Part", "level": 15, "word_type": "noun", "tags": ["body_part", "level_15"]},
  {"guid": "N03_036", "base_target": "foie", "base_source": "ಯಕೃತ್", "corpus": "WORDS3", "group": "Body Part", "level": 15, "word_type": "noun", "tags": ["body_part", "level_15"]},
  {"guid": "N03_037", "base_target": "menton", "base_source": "ಚಿವಟೆ", "corpus": "WORDS3", "group": "Body Part", "level": 15, "word_type": "noun", "tags": ["body_part", "level_15"]},
  {"guid": "N03_038", "base_target": "joue", "base_source": "ಗಡಸು", "corpus": "WORDS3", "group": "Body Part", "level": 15, "word_type": "noun", "tags": ["body_part", "level_15"]},
  {"guid": "N03_039", "base_target": "mâchoire", "base_source": "ಚಿಗುರುಕುಟ್ಟು", "corpus": "WORDS3", "group": "Body Part", "level": 15, "word_type": "noun", "tags": ["body_part", "level_15"]},
  {"guid": "N03_040", "base_target": "gorge", "base_source": "ಕಂಠ", "corpus": "WORDS3", "group": "Body Part", "level": 15, "word_type": "noun", "tags": ["body_part", "level_15"]},
  {"guid": "N03_041", "base_target": "ongle", "base_source": "ನಖ", "corpus": "WORDS3", "group": "Body Part", "level": 15, "word_type": "noun", "tags": ["body_part", "level_15"]},
  {"guid": "N03_042", "base_target": "sueur", "base_source": "ದಮನ", "corpus": "WORDS3", "group": "Body Part", "level": 15, "word_type": "noun", "tags": ["body_part", "level_15"]},
  {"guid": "N03_043", "base_target": "queue", "base_source": "ಐಕ", "corpus": "WORDS3", "group": "Body Part", "level": 15, "word_type": "noun", "tags": ["body_part", "level_15"]},
  {"guid": "N03_044", "base_target": "aile", "base_source": "ಚಕ್ಕೆ", "corpus": "WORDS3", "group": "Body Part", "level": 15, "word_type": "noun", "tags": ["body_part", "level_15"]},
  {"guid": "N03_045", "base_target": "larme", "base_source": "ಆಶ್ರು", "corpus": "WORDS3", "group": "Body Part", "level": 15, "word_type": "noun", "tags": ["body_part", "level_15"]},
  {"guid": "N05_006", "base_target": "forêt", "base_source": "ಕಾಡು", "corpus": "WORDS4", "group": "Plants", "level": 15, "word_type": "noun", "tags": ["plant", "level_15"]},
  {"guid": "N05_007", "base_target": "mauvaise herbe", "base_source": "ಕಿಡ್ನುಗಿಡ", "corpus": "WORDS4", "group": "Plants", "level": 15, "word_type": "noun", "tags": ["plant", "level_15"]},
  {"guid": "N05_008", "base_target": "buisson", "base_source": "ತುಣುಕುಭೂಮಿ (Note: better: ಜೇತೆಗೆ? Wait)", "corpus": "WORDS4", "group": "Plants", "level": 15, "word_type": "noun", "tags": ["plant", "level_15"]},
  {"guid": "N05_009", "base_target": "liane", "base_source": "ದಾರಿಘೇಯ", "corpus": "WORDS4", "group": "Plants", "level": 15, "word_type": "noun", "tags": ["plant", "level_15"]},
  {"guid": "N05_010", "base_target": "mousse", "base_source": "ಕಚ್ಚಿರೆ", "corpus": "WORDS4", "group": "Plants", "level": 15, "word_type": "noun", "tags": ["plant", "level_15"]},
  {"guid": "N05_012", "base_target": "pin", "base_source": "ಚಿಗುರುಗಿಡ (ಚಿನ್ನಗ ಔತ?)", "corpus": "WORDS4", "group": "Plants", "level": 15, "word_type": "noun", "tags": ["plant", "level_15"]},
  {"guid": "N07_018", "base_target": "tente", "base_source": "ಡೇರೆ", "corpus": "WORDS3", "group": "Building/Structure", "level": 15, "word_type": "noun", "tags": ["building_structure", "level_15"]},
  {"guid": "N07_019", "base_target": "grange", "base_source": "ಗೋದಾಮು", "corpus": "WORDS3", "group": "Building/Structure", "level": 15, "word_type": "noun", "tags": ["building_structure", "level_15"]},
  {"guid": "N07_020", "base_target": "gymnase", "base_source": "ವ್ಯಾಯಾಮಶಾಲೆ", "corpus": "WORDS3", "group": "Building/Structure", "level": 15, "word_type": "noun", "tags": ["building_structure", "level_15"]},
  {"guid": "N07_021", "base_target": "théâtre", "base_source": "ರಂಗಮಂದಿರ", "corpus": "WORDS3", "group": "Building/Structure", "level": 15, "word_type": "noun", "tags": ["building_structure", "level_15"]},
  {"guid": "N07_022", "base_target": "aéroport", "base_source": "ವಿಮಾನ ನಿಲ್ದಾಣ", "corpus": "WORDS3", "group": "Building/Structure", "level": 15, "word_type": "noun", "tags": ["building_structure", "level_15"]},
  {"guid": "N07_025", "base_target": "cafétéria", "base_source": "ಕ್ಯಾಂಟೀನ್", "corpus": "WORDS3", "group": "Building/Structure", "level": 15, "word_type": "noun", "tags": ["building_structure", "level_15"]},
  {"guid": "N07_027", "base_target": "cimetière", "base_source": "ಸ್ಮಶಾನ", "corpus": "WORDS3", "group": "Building/Structure", "level": 15, "word_type": "noun", "tags": ["building_structure", "level_15"]},
  {"guid": "N07_029", "base_target": "château", "base_source": "ಕೋಟೆ", "corpus": "WORDS3", "group": "Building/Structure", "level": 15, "word_type": "noun", "tags": ["building_structure", "level_15"]},
  {"guid": "N07_042", "base_target": "salle", "base_source": "ಸಭಾಂಗಣ", "corpus": "WORDS3", "group": "Building/Structure", "level": 15, "word_type": "noun", "tags": ["building_structure", "level_15"]},
  {"guid": "N07_043", "base_target": "tour", "base_source": "ಗೋಪುರ", "corpus": "WORDS3", "group": "Building/Structure", "level": 15, "word_type": "noun", "tags": ["building_structure", "level_15"]},
  {"guid": "N07_044", "base_target": "ferme", "base_source": "ಕೃಷಿ", "corpus": "WORDS3", "group": "Building/Structure", "level": 15, "word_type": "noun", "tags": ["building_structure", "level_15"]},
  {"guid": "N07_045", "base_target": "passage", "base_source": "ಹಾದಿ", "corpus": "WORDS3", "group": "Building/Structure", "level": 15, "word_type": "noun", "tags": ["building_structure", "level_15"]},
  {"guid": "N07_047", "base_target": "chambre", "base_source": "ಕೊಠಡಿ", "corpus": "WORDS3", "group": "Building/Structure", "level": 15, "word_type": "noun", "tags": ["building_structure", "level_15"]},
  {"guid": "N07_048", "base_target": "cellule", "base_source": "ಕೋಣೆ", "corpus": "WORDS3", "group": "Building/Structure", "level": 15, "word_type": "noun", "tags": ["building_structure", "level_15"]},
  {"guid": "N08_027", "base_target": "parapluie", "base_source": "ಚದರು", "corpus": "WORDS3", "group": "Small Movable Object", "level": 15, "word_type": "noun", "tags": ["small_movable_object", "level_15"]},
  {"guid": "N08_028", "base_target": "agrafeuse", "base_source": "ಸ್ಟೇಪ್ಲರ್", "corpus": "WORDS3", "group": "Small Movable Object", "level": 15, "word_type": "noun", "tags": ["small_movable_object", "level_15"]},
  {"guid": "N08_029", "base_target": "oreiller", "base_source": "ತಲೆಹೊಂಬೆ", "corpus": "WORDS3", "group": "Small Movable Object", "level": 15, "word_type": "noun", "tags": ["small_movable_object", "level_15"]},
  {"guid": "N08_030", "base_target": "couverture", "base_source": "ಕಂಬಳಿ", "corpus": "WORDS3", "group": "Small Movable Object", "level": 15, "word_type": "noun", "tags": ["small_movable_object", "level_15"]},
  {"guid": "N08_031", "base_target": "poêle", "base_source": "ತವಾ", "corpus": "WORDS3", "group": "Small Movable Object", "level": 15, "word_type": "noun", "tags": ["small_movable_object", "level_15"]},
  {"guid": "N08_032", "base_target": "vase", "base_source": "ಹೂದಿನಕಟ್ಟೆ", "corpus": "WORDS3", "group": "Small Movable Object", "level": 15, "word_type": "noun", "tags": ["small_movable_object", "level_15"]},
  {"guid": "N08_033", "base_target": "savon", "base_source": "ಸಾಬೂನು", "corpus": "WORDS3", "group": "Small Movable Object", "level": 15, "word_type": "noun", "tags": ["small_movable_object", "level_15"]},
  {"guid": "N08_034", "base_target": "rasoir", "base_source": "ರೇಝರ್", "corpus": "WORDS3", "group": "Small Movable Object", "level": 15, "word_type": "noun", "tags": ["small_movable_object", "level_15"]},
  {"guid": "N08_035", "base_target": "poupée", "base_source": "ಗುಡುಸಿಗೆ", "corpus": "WORDS3", "group": "Small Movable Object", "level": 15, "word_type": "noun", "tags": ["small_movable_object", "level_15"]},
  {"guid": "N08_036", "base_target": "jouet", "base_source": "ಬದುಕ玩？", "corpus": "WORDS3", "group": "Small Movable Object", "level": 15, "word_type": "noun", "tags": ["small_movable_object", "level_15"]},
  {"guid": "N09_018", "base_target": "écharpe", "base_source": "ಸ್ಕಾರ್ಫ್", "corpus": "WORDS3", "group": "Clothing/Accessory", "level": 15, "word_type": "noun", "tags": ["clothing_accessory", "level_15"]},
  {"guid": "N09_019", "base_target": "sandale", "base_source": "ಚಪ್ಪಲಿ", "corpus": "WORDS3", "group": "Clothing/Accessory", "level": 15, "word_type": "noun", "tags": ["clothing_accessory", "level_15"]},
  {"guid": "N09_020", "base_target": "pyjama", "base_source": "ಪೈಜಾಮ", "corpus": "WORDS3", "group": "Clothing/Accessory", "level": 15, "word_type": "noun", "tags": ["clothing_accessory", "level_15"]},
  {"guid": "N09_021", "base_target": "jeans", "base_source": "ಜೀನ್ಸ್", "corpus": "WORDS3", "group": "Clothing/Accessory", "level": 15, "word_type": "noun", "tags": ["clothing_accessory", "level_15"]},
  {"guid": "N09_022", "base_target": "tablier", "base_source": "ಏಪ್ರನ್", "corpus": "WORDS3", "group": "Clothing/Accessory", "level": 15, "word_type": "noun", "tags": ["clothing_accessory", "level_15"]},
  {"guid": "N09_023", "base_target": "imperméable", "base_source": "ಮಳೆಕೋಟು", "corpus": "WORDS3", "group": "Clothing/Accessory", "level": 15, "word_type": "noun", "tags": ["clothing_accessory", "level_15"]},
  {"guid": "N09_024", "base_target": "costume d'affaires", "base_source": "ವ್ಯಾಪಾರ ಸೂಟ್", "corpus": "WORDS3", "group": "Clothing/Accessory", "level": 15, "word_type": "noun", "tags": ["clothing_accessory", "level_15"]},
  {"guid": "N09_025", "base_target": "short", "base_source": "ಶಾರ್ಟ್ಸ್", "corpus": "WORDS3", "group": "Clothing/Accessory", "level": 15, "word_type": "noun", "tags": ["clothing_accessory", "level_15"]},
  {"guid": "N36_001", "base_target": "comptable", "base_source": "ಲೆಕ್ಕಚಾರ", "corpus": "WORDS3", "group": "Occupation", "level": 15, "word_type": "noun", "tags": ["occupation", "level_15"]},
  {"guid": "N36_017", "base_target": "ingénieur", "base_source": "ಅಭಿಯಂತ್ರಿ", "corpus": "WORDS3", "group": "Occupation", "level": 15, "word_type": "noun", "tags": ["occupation", "level_15"]},
  {"guid": "N36_018", "base_target": "avocat", "base_source": "ವಕೀಲ", "corpus": "WORDS3", "group": "Occupation", "level": 15, "word_type": "noun", "tags": ["occupation", "level_15"]},
  {"guid": "N36_023", "base_target": "pilote", "base_source": "ಪೈಲಟ್", "corpus": "WORDS3", "group": "Occupation", "level": 15, "word_type": "noun", "tags": ["occupation", "level_15"]},
  {"guid": "N36_025", "base_target": "mécanicien", "base_source": "ಯಂತ್ರಸ್ಥ", "corpus": "WORDS3", "group": "Occupation", "level": 15, "word_type": "noun", "tags": ["occupation", "level_15"]},
  {"guid": "N36_026", "base_target": "électricien", "base_source": "ವಿದ್ಯುತ್‌ಕಾರ", "corpus": "WORDS3", "group": "Occupation", "level": 15, "word_type": "noun", "tags": ["occupation", "level_15"]},
  {"guid": "N36_027", "base_target": "plombier", "base_source": "ನೀರಿನ ಅಜ್ಜಿಕೆಗಾರ", "corpus": "WORDS3", "group": "Occupation", "level": 15, "word_type": "noun", "tags": ["occupation", "level_15"]},
  {"guid": "N36_028", "base_target": "charpentier", "base_source": "ದರ್ಜಿಹೊಳಪು (Alternatively common: ಚಿಲಿಪಂಪು?)", "corpus": "WORDS3", "group": "Occupation", "level": 15, "word_type": "noun", "tags": ["occupation", "level_15"]},
  {"guid": "N36_032", "base_target": "écrivain", "base_source": "ಲೇಖಕ", "corpus": "WORDS3", "group": "Occupation", "level": 15, "word_type": "noun", "tags": ["occupation", "level_15"]},
  {"guid": "N36_033", "base_target": "journaliste", "base_source": "ಸಂಧರ್ಶನಕಾರ(சೊಂದರ್ಶನಕಾರ)", "corpus": "WORDS3", "group": "Occupation", "level": 15, "word_type": "noun", "tags": ["occupation", "level_15"]},
  {"guid": "N36_034", "base_target": "photographe", "base_source": "ಫೋಟೋಗ್ರಾಫರ್", "corpus": "WORDS3", "group": "Occupation", "level": 15, "word_type": "noun", "tags": ["occupation", "level_15"]},
  {"guid": "N36_035", "base_target": "dentiste", "base_source": "ದಂತವೈದ್ಯ", "corpus": "WORDS3", "group": "Occupation", "level": 15, "word_type": "noun", "tags": ["occupation", "level_15"]},
  {"guid": "N36_036", "base_target": "vétérinaire", "base_source": "ಪ್ರಾಣಿ ವೈದ್ಯ", "corpus": "WORDS3", "group": "Occupation", "level": 15, "word_type": "noun", "tags": ["occupation", "level_15"]},
  {"guid": "N36_041", "base_target": "boulanger", "base_source": "ಬೈಸರ್", "corpus": "WORDS3", "group": "Occupation", "level": 15, "word_type": "noun", "tags": ["occupation", "level_15"]},
  {"guid": "N38_002", "base_target": "racine", "base_source": "ಮೂಲ", "corpus": "WORDS4", "group": "Plant Part", "level": 15, "word_type": "noun", "tags": ["plant_part", "level_15"]},
  {"guid": "N38_003", "base_target": "branche", "base_source": "ಕೊಂಬೆ", "corpus": "WORDS4", "group": "Plant Part", "level": 15, "word_type": "noun", "tags": ["plant_part", "level_15"]},
  {"guid": "N38_004", "base_target": "graine", "base_source": "ಬೀಜ", "corpus": "WORDS4", "group": "Plant Part", "level": 15, "word_type": "noun", "tags": ["plant_part", "level_15"]},
  {"guid": "N38_005", "base_target": "fruit", "base_source": "ಹಣ್ಣು", "corpus": "WORDS4", "group": "Plant Part", "level": 15, "word_type": "noun", "tags": ["plant_part", "level_15"]},
  {"guid": "N38_006", "base_target": "écorce", "base_source": "ಚರ್ಮ", "corpus": "WORDS4", "group": "Plant Part", "level": 15, "word_type": "noun", "tags": ["plant_part", "level_15"]},
  {"guid": "N38_007", "base_target": "pollen", "base_source": "ಪಶುಲತಾ (Note: Kannada common word is 'ಹುಲ್ಲು ಧೂಳು' but lemma 'ಪುಲೆನ್' is 'ಪುಲೆನ್' not appropriate)", "corpus": "WORDS4", "group": "Plant Part", "level": 15, "word_type": "noun", "tags": ["plant_part", "level_15"]},
  {"guid": "N38_008", "base_target": "tronc", "base_source": "ತಣತೆ", "corpus": "WORDS4", "group": "Plant Part", "level": 15, "word_type": "noun", "tags": ["plant_part", "level_15"]},
  {"guid": "N38_009", "base_target": "tige", "base_source": "ಹಸುರುಮುರು", "corpus": "WORDS4", "group": "Plant Part", "level": 15, "word_type": "noun", "tags": ["plant_part", "level_15"]},
  {"guid": "N38_010", "base_target": "pétale", "base_source": "ಪುಷ್ಪಪತ್ರ", "corpus": "WORDS4", "group": "Plant Part", "level": 15, "word_type": "noun", "tags": ["plant_part", "level_15"]},
  {"guid": "N38_011", "base_target": "épine", "base_source": "ಕೆಂಬು", "corpus": "WORDS4", "group": "Plant Part", "level": 15, "word_type": "noun", "tags": ["plant_part", "level_15"]},
  {"guid": "N38_012", "base_target": "bourgeon", "base_source": "ಗುಡ್ಡು", "corpus": "WORDS4", "group": "Plant Part", "level": 15, "word_type": "noun", "tags": ["plant_part", "level_15"]},
  {"guid": "N38_013", "base_target": "fleur", "base_source": "ಪुष್ಪ", "corpus": "WORDS4", "group": "Plant Part", "level": 15, "word_type": "noun", "tags": ["plant_part", "level_15"]},
  {"guid": "N47_004", "base_target": "sol", "base_source": "ನೆಲ", "corpus": "WORDS4", "group": "Building Part", "level": 15, "word_type": "noun", "tags": ["building_part", "level_15"]},
  {"guid": "N47_005", "base_target": "plafond", "base_source": "ಚಾವಣಿ", "corpus": "WORDS4", "group": "Building Part", "level": 15, "word_type": "noun", "tags": ["building_part", "level_15"]},
  {"guid": "N47_006", "base_target": "toit", "base_source": "ಛಾವಣಿ", "corpus": "WORDS4", "group": "Building Part", "level": 15, "word_type": "noun", "tags": ["building_part", "level_15"]},
  {"guid": "N47_007", "base_target": "escalier", "base_source": "ಮೆಟ್ಟಿಲುಗಳು", "corpus": "WORDS4", "group": "Building Part", "level": 15, "word_type": "noun", "tags": ["building_part", "level_15"]},
  {"guid": "N47_008", "base_target": "portail", "base_source": "ಗೇಟು", "corpus": "WORDS4", "group": "Building Part", "level": 15, "word_type": "noun", "tags": ["building_part", "level_15"]},
  {"guid": "N47_011", "base_target": "arc", "base_source": "ಕಮಾನು", "corpus": "WORDS4", "group": "Building Part", "level": 15, "word_type": "noun", "tags": ["building_part", "level_15"]},
  {"guid": "N47_012", "base_target": "palier", "base_source": "ಮೆಟ್ಟಿಲ ಮಧ್ಯ ಜಾಗ", "corpus": "WORDS4", "group": "Building Part", "level": 15, "word_type": "noun", "tags": ["building_part", "level_15"]},
  {"guid": "N47_013", "base_target": "cheminée", "base_source": "ಚಿಮಣಿ", "corpus": "WORDS4", "group": "Building Part", "level": 15, "word_type": "noun", "tags": ["building_part", "level_15"]},
  {"guid": "N47_014", "base_target": "balcon", "base_source": "ಬಾಲ್ಕನಿ", "corpus": "WORDS4", "group": "Building Part", "level": 15, "word_type": "noun", "tags": ["building_part", "level_15"]},
  {"guid": "N47_015", "base_target": "pilier", "base_source": "ಕಂಬ", "corpus": "WORDS4", "group": "Building Part", "level": 15, "word_type": "noun", "tags": ["building_part", "level_15"]},
  {"guid": "N47_016", "base_target": "clôture", "base_source": "ಬೇಲಿ", "corpus": "WORDS4", "group": "Building Part", "level": 15, "word_type": "noun", "tags": ["building_part", "level_15"]}
]
